{"commentary": {"count": 308, "pageIndex": 1, "pageSize": 25, "pageCount": 13, "items": [{"id": "110", "clock": "00:00", "date": "2018-07-22T09:30", "playType": {"id": "2", "description": "no run"}, "team": {"id": "25", "name": "Bangladesh", "abbreviation": "BDESH", "displayName": "Bangladesh"}, "mediaId": 0, "period": 1, "periodText": "1st innings", "preText": "<B>1.50pm </b> A side that didn't last five days combined across two Tests suddenly transformed their game like they'd used a magic wand. Welcome back to the chase. Akshay's taking a breather. I'm back rejuvenated to take you through to drinks. We're still 10 minutes away from a resumption.", "text": "back of a length, jumps and tucks into the on side", "postText": "", "shortText": "Russell to Tamim Iqbal, no run", "homeScore": "0/0", "awayScore": "0", "scoreValue": 0, "sequence": 100001, "athletesInvolved": [{"id": "56194", "name": "Tamim Iqbal", "shortName": "Tamim", "displayName": "Tamim Iqbal"}, {"id": "276298", "name": "Andre Russell", "shortName": "Russell", "displayName": "Andre Russell"}], "speedKPH": "", "speedMPH": "", "bowler": {"athlete": {"id": "276298", "name": "Andre Russell", "shortName": "Russell", "fullName": "Andre Dwayne Russell", "displayName": "Andre Russell"}, "team": {"id": "4", "name": "West Indies", "abbreviation": "WI", "displayName": "West Indies"}, "maidens": 0, "balls": 1, "wickets": 0, "overs": 0.1, "conceded": 0}, "otherBowler": {"athlete": {}, "team": {}, "maidens": 0, "balls": 0, "wickets": 0, "conceded": 0}, "batsman": {"athlete": {"id": "56194", "name": "Tamim Iqbal", "shortName": "Tamim", "fullName": "Tamim Iqbal Khan", "displayName": "Tamim Iqbal"}, "team": {"id": "25", "name": "Bangladesh", "abbreviation": "BDESH", "displayName": "Bangladesh"}, "totalRuns": 0, "faced": 1, "fours": 0, "runs": 0, "sixes": 0}, "otherBatsman": {"athlete": {"id": "380354", "name": "Anamul Haque", "shortName": "Anamul", "fullName": "Mohammad Anamul Haque Bijoy", "displayName": "Anamul Haque"}, "team": {"id": "25", "name": "Bangladesh", "abbreviation": "BDESH", "displayName": "Bangladesh"}, "totalRuns": 0, "faced": 0, "fours": 0, "runs": 0, "sixes": 0}, "innings": {"id": "206970", "runRate": 0.0, "remainingBalls": 299, "byes": 0, "number": 1, "balls": 1, "noBalls": 0, "wickets": 0, "legByes": 0, "ballLimit": 300, "target": 0, "session": 1, "day": 1, "fallOfWickets": 0, "remainingOvers": 0.0, "totalRuns": 0, "wides": 0, "runs": 0}, "over": {"ball": 1, "balls": 6, "complete": false, "limit": 50.0, "maiden": 0, "noBall": 0, "wide": 0, "byes": 0, "legByes": 0, "number": 1, "runs": 1, "wickets": 0, "overs": 0.1, "actual": 0.1, "unique": 0.01}, "dismissal": {"dismissal": false, "bowled": false, "type": "", "bowler": {"athlete": {"id": "276298", "name": "Andre Russell", "shortName": "Russell", "fullName": "Andre Dwayne Russell", "displayName": "Andre Russell"}}, "batsman": {"athlete": {"id": "56194", "name": "Tamim Iqbal", "shortName": "Tamim", "fullName": "Tamim Iqbal Khan", "displayName": "Tamim Iqbal"}}, "fielder": {"athlete": {}}, "minutes": 0, "retiredText": ""}}, {"id": "120", "clock": "00:00", "date": "2018-07-22T09:30", "playType": {"id": "2", "description": "no run"}, "team": {"id": "25", "name": "Bangladesh", "abbreviation": "BDESH", "displayName": "Bangladesh"}, "mediaId": 0, "period": 1, "periodText": "1st innings", "preText": "", "text": "nice bowling. Length ball, seams away off the deck and rips past the outside edge of Tamim half-heartedly playing forward", "postText": "", "shortText": "Russell to Tamim Iqbal, no run", "homeScore": "0/0", "awayScore": "0", "scoreValue": 0, "sequence": 100002, "athletesInvolved": [{"id": "56194", "name": "Tamim Iqbal", "shortName": "Tamim", "displayName": "Tamim Iqbal"}, {"id": "276298", "name": "Andre Russell", "shortName": "Russell", "displayName": "Andre Russell"}], "speedKPH": "", "speedMPH": "", "bowler": {"athlete": {"id": "276298", "name": "Andre Russell", "shortName": "Russell", "fullName": "Andre Dwayne Russell", "displayName": "Andre Russell"}, "team": {"id": "4", "name": "West Indies", "abbreviation": "WI", "displayName": "West Indies"}, "maidens": 0, "balls": 2, "wickets": 0, "overs": 0.2, "conceded": 0}, "otherBowler": {"athlete": {}, "team": {}, "maidens": 0, "balls": 0, "wickets": 0, "conceded": 0}, "batsman": {"athlete": {"id": "56194", "name": "Tamim Iqbal", "shortName": "Tamim", "fullName": "Tamim Iqbal Khan", "displayName": "Tamim Iqbal"}, "team": {"id": "25", "name": "Bangladesh", "abbreviation": "BDESH", "displayName": "Bangladesh"}, "totalRuns": 0, "faced": 2, "fours": 0, "runs": 0, "sixes": 0}, "otherBatsman": {"athlete": {"id": "380354", "name": "Anamul Haque", "shortName": "Anamul", "fullName": "Mohammad Anamul Haque Bijoy", "displayName": "Anamul Haque"}, "team": {"id": "25", "name": "Bangladesh", "abbreviation": "BDESH", "displayName": "Bangladesh"}, "totalRuns": 0, "faced": 0, "fours": 0, "runs": 0, "sixes": 0}, "innings": {"id": "206970", "runRate": 0.0, "remainingBalls": 298, "byes": 0, "number": 1, "balls": 2, "noBalls": 0, "wickets": 0, "legByes": 0, "ballLimit": 300, "target": 0, "session": 1, "day": 1, "fallOfWickets": 0, "remainingOvers": 0.0, "totalRuns": 0, "wides": 0, "runs": 0}, "over": {"ball": 2, "balls": 6, "complete": false, "limit": 50.0, "maiden": 0, "noBall": 0, "wide": 0, "byes": 0, "legByes": 0, "number": 1, "runs": 1, "wickets": 0, "overs": 0.2, "actual": 0.2, "unique": 0.02}, "dismissal": {"dismissal": false, "bowled": false, "type": "", "bowler": {"athlete": {"id": "276298", "name": "Andre Russell", "shortName": "Russell", "fullName": "Andre Dwayne Russell", "displayName": "Andre Russell"}}, "batsman": {"athlete": {"id": "56194", "name": "Tamim Iqbal", "shortName": "Tamim", "fullName": "Tamim Iqbal Khan", "displayName": "Tamim Iqbal"}}, "fielder": {"athlete": {}}, "minutes": 0, "retiredText": ""}}, {"id": "130", "clock": "00:00", "date": "2018-07-22T09:30", "playType": {"id": "2", "description": "no run"}, "team": {"id": "25", "name": "Bangladesh", "abbreviation": "BDESH", "displayName": "Bangladesh"}, "mediaId": 0, "period": 1, "periodText": "1st innings", "preText": "", "text": "good length on off, takes a solid stride forward and blocks", "postText": "", "shortText": "Russell to Tamim Iqbal, no run", "homeScore": "0/0", "awayScore": "0", "scoreValue": 0, "sequence": 100003, "athletesInvolved": [{"id": "56194", "name": "Tamim Iqbal", "shortName": "Tamim", "displayName": "Tamim Iqbal"}, {"id": "276298", "name": "Andre Russell", "shortName": "Russell", "displayName": "Andre Russell"}], "speedKPH": "", "speedMPH": "", "bowler": {"athlete": {"id": "276298", "name": "Andre Russell", "shortName": "Russell", "fullName": "Andre Dwayne Russell", "displayName": "Andre Russell"}, "team": {"id": "4", "name": "West Indies", "abbreviation": "WI", "displayName": "West Indies"}, "maidens": 0, "balls": 3, "wickets": 0, "overs": 0.3, "conceded": 0}, "otherBowler": {"athlete": {}, "team": {}, "maidens": 0, "balls": 0, "wickets": 0, "conceded": 0}, "batsman": {"athlete": {"id": "56194", "name": "Tamim Iqbal", "shortName": "Tamim", "fullName": "Tamim Iqbal Khan", "displayName": "Tamim Iqbal"}, "team": {"id": "25", "name": "Bangladesh", "abbreviation": "BDESH", "displayName": "Bangladesh"}, "totalRuns": 0, "faced": 3, "fours": 0, "runs": 0, "sixes": 0}, "otherBatsman": {"athlete": {"id": "380354", "name": "Anamul Haque", "shortName": "Anamul", "fullName": "Mohammad Anamul Haque Bijoy", "displayName": "Anamul Haque"}, "team": {"id": "25", "name": "Bangladesh", "abbreviation": "BDESH", "displayName": "Bangladesh"}, "totalRuns": 0, "faced": 0, "fours": 0, "runs": 0, "sixes": 0}, "innings": {"id": "206970", "runRate": 0.0, "remainingBalls": 297, "byes": 0, "number": 1, "balls": 3, "noBalls": 0, "wickets": 0, "legByes": 0, "ballLimit": 300, "target": 0, "session": 1, "day": 1, "fallOfWickets": 0, "remainingOvers": 0.0, "totalRuns": 0, "wides": 0, "runs": 0}, "over": {"ball": 3, "balls": 6, "complete": false, "limit": 50.0, "maiden": 0, "noBall": 0, "wide": 0, "byes": 0, "legByes": 0, "number": 1, "runs": 1, "wickets": 0, "overs": 0.3, "actual": 0.3, "unique": 0.03}, "dismissal": {"dismissal": false, "bowled": false, "type": "", "bowler": {"athlete": {"id": "276298", "name": "Andre Russell", "shortName": "Russell", "fullName": "Andre Dwayne Russell", "displayName": "Andre Russell"}}, "batsman": {"athlete": {"id": "56194", "name": "Tamim Iqbal", "shortName": "Tamim", "fullName": "Tamim Iqbal Khan", "displayName": "Tamim Iqbal"}}, "fielder": {"athlete": {}}, "minutes": 0, "retiredText": ""}}, {"id": "140", "clock": "00:00", "date": "2018-07-22T09:30", "playType": {"id": "2", "description": "no run"}, "team": {"id": "25", "name": "Bangladesh", "abbreviation": "BDESH", "displayName": "Bangladesh"}, "mediaId": 0, "period": 1, "periodText": "1st innings", "preText": "", "text": "good length on off, defended back", "postText": "", "shortText": "Russell to Tamim Iqbal, no run", "homeScore": "0/0", "awayScore": "0", "scoreValue": 0, "sequence": 100004, "athletesInvolved": [{"id": "56194", "name": "Tamim Iqbal", "shortName": "Tamim", "displayName": "Tamim Iqbal"}, {"id": "276298", "name": "Andre Russell", "shortName": "Russell", "displayName": "Andre Russell"}], "speedKPH": "", "speedMPH": "", "bowler": {"athlete": {"id": "276298", "name": "Andre Russell", "shortName": "Russell", "fullName": "Andre Dwayne Russell", "displayName": "Andre Russell"}, "team": {"id": "4", "name": "West Indies", "abbreviation": "WI", "displayName": "West Indies"}, "maidens": 0, "balls": 4, "wickets": 0, "overs": 0.4, "conceded": 0}, "otherBowler": {"athlete": {}, "team": {}, "maidens": 0, "balls": 0, "wickets": 0, "conceded": 0}, "batsman": {"athlete": {"id": "56194", "name": "Tamim Iqbal", "shortName": "Tamim", "fullName": "Tamim Iqbal Khan", "displayName": "Tamim Iqbal"}, "team": {"id": "25", "name": "Bangladesh", "abbreviation": "BDESH", "displayName": "Bangladesh"}, "totalRuns": 0, "faced": 4, "fours": 0, "runs": 0, "sixes": 0}, "otherBatsman": {"athlete": {"id": "380354", "name": "Anamul Haque", "shortName": "Anamul", "fullName": "Mohammad Anamul Haque Bijoy", "displayName": "Anamul Haque"}, "team": {"id": "25", "name": "Bangladesh", "abbreviation": "BDESH", "displayName": "Bangladesh"}, "totalRuns": 0, "faced": 0, "fours": 0, "runs": 0, "sixes": 0}, "innings": {"id": "206970", "runRate": 0.0, "remainingBalls": 296, "byes": 0, "number": 1, "balls": 4, "noBalls": 0, "wickets": 0, "legByes": 0, "ballLimit": 300, "target": 0, "session": 1, "day": 1, "fallOfWickets": 0, "remainingOvers": 0.0, "totalRuns": 0, "wides": 0, "runs": 0}, "over": {"ball": 4, "balls": 6, "complete": false, "limit": 50.0, "maiden": 0, "noBall": 0, "wide": 0, "byes": 0, "legByes": 0, "number": 1, "runs": 1, "wickets": 0, "overs": 0.4, "actual": 0.4, "unique": 0.04}, "dismissal": {"dismissal": false, "bowled": false, "type": "", "bowler": {"athlete": {"id": "276298", "name": "Andre Russell", "shortName": "Russell", "fullName": "Andre Dwayne Russell", "displayName": "Andre Russell"}}, "batsman": {"athlete": {"id": "56194", "name": "Tamim Iqbal", "shortName": "Tamim", "fullName": "Tamim Iqbal Khan", "displayName": "Tamim Iqbal"}}, "fielder": {"athlete": {}}, "minutes": 0, "retiredText": ""}}, {"id": "150", "clock": "00:00", "date": "2018-07-22T09:30", "playType": {"id": "2", "description": "no run"}, "team": {"id": "25", "name": "Bangladesh", "abbreviation": "BDESH", "displayName": "Bangladesh"}, "mediaId": 0, "period": 1, "periodText": "1st innings", "preText": "", "text": "nice mix-up. Follows up the length deliveries with a short one viciously climbing and forcing Tamim to arch back", "postText": "", "shortText": "Russell to Tamim Iqbal, no run", "homeScore": "0/0", "awayScore": "0", "scoreValue": 0, "sequence": 100005, "athletesInvolved": [{"id": "56194", "name": "Tamim Iqbal", "shortName": "Tamim", "displayName": "Tamim Iqbal"}, {"id": "276298", "name": "Andre Russell", "shortName": "Russell", "displayName": "Andre Russell"}], "speedKPH": "", "speedMPH": "", "bowler": {"athlete": {"id": "276298", "name": "Andre Russell", "shortName": "Russell", "fullName": "Andre Dwayne Russell", "displayName": "Andre Russell"}, "team": {"id": "4", "name": "West Indies", "abbreviation": "WI", "displayName": "West Indies"}, "maidens": 0, "balls": 5, "wickets": 0, "overs": 0.5, "conceded": 0}, "otherBowler": {"athlete": {}, "team": {}, "maidens": 0, "balls": 0, "wickets": 0, "conceded": 0}, "batsman": {"athlete": {"id": "56194", "name": "Tamim Iqbal", "shortName": "Tamim", "fullName": "Tamim Iqbal Khan", "displayName": "Tamim Iqbal"}, "team": {"id": "25", "name": "Bangladesh", "abbreviation": "BDESH", "displayName": "Bangladesh"}, "totalRuns": 0, "faced": 5, "fours": 0, "runs": 0, "sixes": 0}, "otherBatsman": {"athlete": {"id": "380354", "name": "Anamul Haque", "shortName": "Anamul", "fullName": "Mohammad Anamul Haque Bijoy", "displayName": "Anamul Haque"}, "team": {"id": "25", "name": "Bangladesh", "abbreviation": "BDESH", "displayName": "Bangladesh"}, "totalRuns": 0, "faced": 0, "fours": 0, "runs": 0, "sixes": 0}, "innings": {"id": "206970", "runRate": 0.0, "remainingBalls": 295, "byes": 0, "number": 1, "balls": 5, "noBalls": 0, "wickets": 0, "legByes": 0, "ballLimit": 300, "target": 0, "session": 1, "day": 1, "fallOfWickets": 0, "remainingOvers": 0.0, "totalRuns": 0, "wides": 0, "runs": 0}, "over": {"ball": 5, "balls": 6, "complete": false, "limit": 50.0, "maiden": 0, "noBall": 0, "wide": 0, "byes": 0, "legByes": 0, "number": 1, "runs": 1, "wickets": 0, "overs": 0.5, "actual": 0.5, "unique": 0.05}, "dismissal": {"dismissal": false, "bowled": false, "type": "", "bowler": {"athlete": {"id": "276298", "name": "Andre Russell", "shortName": "Russell", "fullName": "Andre Dwayne Russell", "displayName": "Andre Russell"}}, "batsman": {"athlete": {"id": "56194", "name": "Tamim Iqbal", "shortName": "Tamim", "fullName": "Tamim Iqbal Khan", "displayName": "Tamim Iqbal"}}, "fielder": {"athlete": {}}, "minutes": 0, "retiredText": ""}}, {"id": "160", "clock": "00:00", "date": "2018-07-22T09:30", "playType": {"id": "6", "description": "wide"}, "team": {"id": "25", "name": "Bangladesh", "abbreviation": "BDESH", "displayName": "Bangladesh"}, "mediaId": 0, "period": 1, "periodText": "1st innings", "preText": "", "text": "back of a length, skips down leg as Tamim misses the glance", "postText": "", "shortText": "Russell to Tamim Iqbal, 1 wide", "homeScore": "1/0", "awayScore": "0", "scoreValue": 1, "sequence": 100006, "athletesInvolved": [{"id": "56194", "name": "Tamim Iqbal", "shortName": "Tamim", "displayName": "Tamim Iqbal"}, {"id": "276298", "name": "Andre Russell", "shortName": "Russell", "displayName": "Andre Russell"}], "speedKPH": "", "speedMPH": "", "bowler": {"athlete": {"id": "276298", "name": "Andre Russell", "shortName": "Russell", "fullName": "Andre Dwayne Russell", "displayName": "Andre Russell"}, "team": {"id": "4", "name": "West Indies", "abbreviation": "WI", "displayName": "West Indies"}, "maidens": 0, "balls": 5, "wickets": 0, "overs": 0.5, "conceded": 1}, "otherBowler": {"athlete": {}, "team": {}, "maidens": 0, "balls": 0, "wickets": 0, "conceded": 0}, "batsman": {"athlete": {"id": "56194", "name": "Tamim Iqbal", "shortName": "Tamim", "fullName": "Tamim Iqbal Khan", "displayName": "Tamim Iqbal"}, "team": {"id": "25", "name": "Bangladesh", "abbreviation": "BDESH", "displayName": "Bangladesh"}, "totalRuns": 0, "faced": 5, "fours": 0, "runs": 1, "sixes": 0}, "otherBatsman": {"athlete": {"id": "380354", "name": "Anamul Haque", "shortName": "Anamul", "fullName": "Mohammad Anamul Haque Bijoy", "displayName": "Anamul Haque"}, "team": {"id": "25", "name": "Bangladesh", "abbreviation": "BDESH", "displayName": "Bangladesh"}, "totalRuns": 0, "faced": 0, "fours": 0, "runs": 0, "sixes": 0}, "innings": {"id": "206970", "runRate": 1.2, "remainingBalls": 295, "byes": 0, "number": 1, "balls": 5, "noBalls": 0, "wickets": 0, "legByes": 0, "ballLimit": 300, "target": 0, "session": 1, "day": 1, "fallOfWickets": 0, "remainingOvers": 0.0, "totalRuns": 1, "wides": 1, "runs": 1}, "over": {"ball": 6, "balls": 6, "complete": false, "limit": 50.0, "maiden": 0, "noBall": 0, "wide": 1, "byes": 0, "legByes": 0, "number": 1, "runs": 1, "wickets": 0, "overs": 0.5, "actual": 0.6, "unique": 0.06}, "dismissal": {"dismissal": false, "bowled": false, "type": "", "bowler": {"athlete": {"id": "276298", "name": "Andre Russell", "shortName": "Russell", "fullName": "Andre Dwayne Russell", "displayName": "Andre Russell"}}, "batsman": {"athlete": {"id": "56194", "name": "Tamim Iqbal", "shortName": "Tamim", "fullName": "Tamim Iqbal Khan", "displayName": "Tamim Iqbal"}}, "fielder": {"athlete": {}}, "minutes": 0, "retiredText": ""}}, {"id": "170", "clock": "00:00", "date": "2018-07-22T09:30", "playType": {"id": "2", "description": "no run"}, "team": {"id": "25", "name": "Bangladesh", "abbreviation": "BDESH", "displayName": "Bangladesh"}, "mediaId": 0, "period": 1, "periodText": "1st innings", "preText": "", "text": "short of a length on off, blocked into the off side", "postText": "", "shortText": "Russell to Tamim Iqbal, no run", "homeScore": "1/0", "awayScore": "0", "scoreValue": 0, "sequence": 100007, "athletesInvolved": [{"id": "56194", "name": "Tamim Iqbal", "shortName": "Tamim", "displayName": "Tamim Iqbal"}, {"id": "276298", "name": "Andre Russell", "shortName": "Russell", "displayName": "Andre Russell"}], "speedKPH": "", "speedMPH": "", "bowler": {"athlete": {"id": "276298", "name": "Andre Russell", "shortName": "Russell", "fullName": "Andre Dwayne Russell", "displayName": "Andre Russell"}, "team": {"id": "4", "name": "West Indies", "abbreviation": "WI", "displayName": "West Indies"}, "maidens": 0, "balls": 6, "wickets": 0, "overs": 1.0, "conceded": 1}, "otherBowler": {"athlete": {}, "team": {}, "maidens": 0, "balls": 0, "wickets": 0, "conceded": 0}, "batsman": {"athlete": {"id": "56194", "name": "Tamim Iqbal", "shortName": "Tamim", "fullName": "Tamim Iqbal Khan", "displayName": "Tamim Iqbal"}, "team": {"id": "25", "name": "Bangladesh", "abbreviation": "BDESH", "displayName": "Bangladesh"}, "totalRuns": 0, "faced": 6, "fours": 0, "runs": 1, "sixes": 0}, "otherBatsman": {"athlete": {"id": "380354", "name": "Anamul Haque", "shortName": "Anamul", "fullName": "Mohammad Anamul Haque Bijoy", "displayName": "Anamul Haque"}, "team": {"id": "25", "name": "Bangladesh", "abbreviation": "BDESH", "displayName": "Bangladesh"}, "totalRuns": 0, "faced": 0, "fours": 0, "runs": 0, "sixes": 0}, "innings": {"id": "206970", "runRate": 1.0, "remainingBalls": 294, "byes": 0, "number": 1, "balls": 6, "noBalls": 0, "wickets": 0, "legByes": 0, "ballLimit": 300, "target": 0, "session": 1, "day": 1, "fallOfWickets": 0, "remainingOvers": 0.0, "totalRuns": 0, "wides": 0, "runs": 1}, "over": {"ball": 7, "balls": 6, "complete": true, "limit": 50.0, "maiden": 0, "noBall": 0, "wide": 0, "byes": 0, "legByes": 0, "number": 1, "runs": 1, "wickets": 0, "overs": 0.6, "actual": 0.6, "unique": 0.07}, "dismissal": {"dismissal": false, "bowled": false, "type": "", "bowler": {"athlete": {"id": "276298", "name": "Andre Russell", "shortName": "Russell", "fullName": "Andre Dwayne Russell", "displayName": "Andre Russell"}}, "batsman": {"athlete": {"id": "56194", "name": "Tamim Iqbal", "shortName": "Tamim", "fullName": "Tamim Iqbal Khan", "displayName": "Tamim Iqbal"}}, "fielder": {"athlete": {}}, "minutes": 0, "retiredText": ""}}, {"id": "11010", "clock": "00:00", "date": "2018-07-22T09:30", "playType": {"id": "2", "description": "no run"}, "team": {"id": "25", "name": "Bangladesh", "abbreviation": "BDESH", "displayName": "Bangladesh"}, "mediaId": 0, "period": 1, "periodText": "1st innings", "preText": "Holder\n\nReaders in India can watch this match LIVE <a href=\"http://www.espn.in/watch/\" target=\"_blank\">here</a>.", "text": "straightens from a back of a length and the extra bounce catches him on the stomach area", "postText": "", "shortText": "Holder to Anamul Haque, no run", "homeScore": "1/0", "awayScore": "0", "scoreValue": 0, "sequence": 100101, "athletesInvolved": [{"id": "380354", "name": "Anamul Haque", "shortName": "Anamul", "displayName": "Anamul Haque"}, {"id": "391485", "name": "Jason Holder", "shortName": "Holder", "displayName": "Jason Holder"}], "speedKPH": "", "speedMPH": "", "bowler": {"athlete": {"id": "391485", "name": "Jason Holder", "shortName": "Holder", "fullName": "Jason Omar Holder", "displayName": "Jason Holder"}, "team": {"id": "4", "name": "West Indies", "abbreviation": "WI", "displayName": "West Indies"}, "maidens": 0, "balls": 1, "wickets": 0, "overs": 0.1, "conceded": 0}, "otherBowler": {"athlete": {"id": "276298", "name": "Andre Russell", "shortName": "Russell", "fullName": "Andre Dwayne Russell", "displayName": "Andre Russell"}, "team": {"id": "4", "name": "West Indies", "abbreviation": "WI", "displayName": "West Indies"}, "maidens": 0, "balls": 6, "wickets": 0, "overs": 1.0, "conceded": 1}, "batsman": {"athlete": {"id": "380354", "name": "Anamul Haque", "shortName": "Anamul", "fullName": "Mohammad Anamul Haque Bijoy", "displayName": "Anamul Haque"}, "team": {"id": "25", "name": "Bangladesh", "abbreviation": "BDESH", "displayName": "Bangladesh"}, "totalRuns": 0, "faced": 1, "fours": 0, "runs": 1, "sixes": 0}, "otherBatsman": {"athlete": {"id": "56194", "name": "Tamim Iqbal", "shortName": "Tamim", "fullName": "Tamim Iqbal Khan", "displayName": "Tamim Iqbal"}, "team": {"id": "25", "name": "Bangladesh", "abbreviation": "BDESH", "displayName": "Bangladesh"}, "totalRuns": 0, "faced": 6, "fours": 0, "runs": 0, "sixes": 0}, "innings": {"id": "206970", "runRate": 0.85, "remainingBalls": 293, "byes": 0, "number": 1, "balls": 7, "noBalls": 0, "wickets": 0, "legByes": 0, "ballLimit": 300, "target": 0, "session": 1, "day": 1, "fallOfWickets": 0, "remainingOvers": 0.0, "totalRuns": 0, "wides": 0, "runs": 1}, "over": {"ball": 1, "balls": 6, "complete": false, "limit": 50.0, "maiden": 0, "noBall": 0, "wide": 0, "byes": 0, "legByes": 0, "number": 2, "runs": 1, "wickets": 1, "overs": 1.1, "actual": 1.1, "unique": 1.01}, "dismissal": {"dismissal": false, "bowled": false, "type": "", "bowler": {"athlete": {"id": "391485", "name": "Jason Holder", "shortName": "Holder", "fullName": "Jason Omar Holder", "displayName": "Jason Holder"}}, "batsman": {"athlete": {"id": "380354", "name": "Anamul Haque", "shortName": "Anamul", "fullName": "Mohammad Anamul Haque Bijoy", "displayName": "Anamul Haque"}}, "fielder": {"athlete": {}}, "minutes": 0, "retiredText": ""}}, {"id": "11020", "clock": "00:00", "date": "2018-07-22T09:30", "playType": {"id": "2", "description": "no run"}, "team": {"id": "25", "name": "Bangladesh", "abbreviation": "BDESH", "displayName": "Bangladesh"}, "mediaId": 0, "period": 1, "periodText": "1st innings", "preText": "", "text": "sharp swing away from a fifth or sixth-stump line, left alone", "postText": "", "shortText": "Holder to Anamul Haque, no run", "homeScore": "1/0", "awayScore": "0", "scoreValue": 0, "sequence": 100102, "athletesInvolved": [{"id": "380354", "name": "Anamul Haque", "shortName": "Anamul", "displayName": "Anamul Haque"}, {"id": "391485", "name": "Jason Holder", "shortName": "Holder", "displayName": "Jason Holder"}], "speedKPH": "", "speedMPH": "", "bowler": {"athlete": {"id": "391485", "name": "Jason Holder", "shortName": "Holder", "fullName": "Jason Omar Holder", "displayName": "Jason Holder"}, "team": {"id": "4", "name": "West Indies", "abbreviation": "WI", "displayName": "West Indies"}, "maidens": 0, "balls": 2, "wickets": 0, "overs": 0.2, "conceded": 0}, "otherBowler": {"athlete": {"id": "276298", "name": "Andre Russell", "shortName": "Russell", "fullName": "Andre Dwayne Russell", "displayName": "Andre Russell"}, "team": {"id": "4", "name": "West Indies", "abbreviation": "WI", "displayName": "West Indies"}, "maidens": 0, "balls": 6, "wickets": 0, "overs": 1.0, "conceded": 1}, "batsman": {"athlete": {"id": "380354", "name": "Anamul Haque", "shortName": "Anamul", "fullName": "Mohammad Anamul Haque Bijoy", "displayName": "Anamul Haque"}, "team": {"id": "25", "name": "Bangladesh", "abbreviation": "BDESH", "displayName": "Bangladesh"}, "totalRuns": 0, "faced": 2, "fours": 0, "runs": 1, "sixes": 0}, "otherBatsman": {"athlete": {"id": "56194", "name": "Tamim Iqbal", "shortName": "Tamim", "fullName": "Tamim Iqbal Khan", "displayName": "Tamim Iqbal"}, "team": {"id": "25", "name": "Bangladesh", "abbreviation": "BDESH", "displayName": "Bangladesh"}, "totalRuns": 0, "faced": 6, "fours": 0, "runs": 0, "sixes": 0}, "innings": {"id": "206970", "runRate": 0.75, "remainingBalls": 292, "byes": 0, "number": 1, "balls": 8, "noBalls": 0, "wickets": 0, "legByes": 0, "ballLimit": 300, "target": 0, "session": 1, "day": 1, "fallOfWickets": 0, "remainingOvers": 0.0, "totalRuns": 0, "wides": 0, "runs": 1}, "over": {"ball": 2, "balls": 6, "complete": false, "limit": 50.0, "maiden": 0, "noBall": 0, "wide": 0, "byes": 0, "legByes": 0, "number": 2, "runs": 1, "wickets": 1, "overs": 1.2, "actual": 1.2, "unique": 1.02}, "dismissal": {"dismissal": false, "bowled": false, "type": "", "bowler": {"athlete": {"id": "391485", "name": "Jason Holder", "shortName": "Holder", "fullName": "Jason Omar Holder", "displayName": "Jason Holder"}}, "batsman": {"athlete": {"id": "380354", "name": "Anamul Haque", "shortName": "Anamul", "fullName": "Mohammad Anamul Haque Bijoy", "displayName": "Anamul Haque"}}, "fielder": {"athlete": {}}, "minutes": 0, "retiredText": ""}}, {"id": "11030", "clock": "00:00", "date": "2018-07-22T09:30", "playType": {"id": "9", "description": "out"}, "team": {"id": "25", "name": "Bangladesh", "abbreviation": "BDESH", "displayName": "Bangladesh"}, "mediaId": 0, "period": 1, "periodText": "1st innings", "preText": "", "text": "<b>edged and taken</b>. Holder's given Bangladesh a miserable time all tour. And this is a top delivery. Pitched up and inviting the batsman forward, and as Anamul pushes forward, it jags away and shaves the outside of the bat to settle into the hands of second slip", "postText": "", "shortText": "Holder to Anamul Haque, OUT", "homeScore": "1/1", "awayScore": "0", "scoreValue": 0, "sequence": 100103, "athletesInvolved": [{"id": "380354", "name": "Anamul Haque", "shortName": "Anamul", "displayName": "Anamul Haque"}, {"id": "391485", "name": "Jason Holder", "shortName": "Holder", "displayName": "Jason Holder"}, {"id": "315594", "name": "Ashley Nurse", "shortName": "Nurse", "displayName": "Ashley Nurse"}], "speedKPH": "", "speedMPH": "", "bowler": {"athlete": {"id": "391485", "name": "Jason Holder", "shortName": "Holder", "fullName": "Jason Omar Holder", "displayName": "Jason Holder"}, "team": {"id": "4", "name": "West Indies", "abbreviation": "WI", "displayName": "West Indies"}, "maidens": 0, "balls": 3, "wickets": 1, "overs": 0.3, "conceded": 0}, "otherBowler": {"athlete": {"id": "276298", "name": "Andre Russell", "shortName": "Russell", "fullName": "Andre Dwayne Russell", "displayName": "Andre Russell"}, "team": {"id": "4", "name": "West Indies", "abbreviation": "WI", "displayName": "West Indies"}, "maidens": 0, "balls": 6, "wickets": 0, "overs": 1.0, "conceded": 1}, "batsman": {"athlete": {"id": "380354", "name": "Anamul Haque", "shortName": "Anamul", "fullName": "Mohammad Anamul Haque Bijoy", "displayName": "Anamul Haque"}, "team": {"id": "25", "name": "Bangladesh", "abbreviation": "BDESH", "displayName": "Bangladesh"}, "totalRuns": 0, "faced": 3, "fours": 0, "runs": 1, "sixes": 0}, "otherBatsman": {"athlete": {"id": "56194", "name": "Tamim Iqbal", "shortName": "Tamim", "fullName": "Tamim Iqbal Khan", "displayName": "Tamim Iqbal"}, "team": {"id": "25", "name": "Bangladesh", "abbreviation": "BDESH", "displayName": "Bangladesh"}, "totalRuns": 0, "faced": 6, "fours": 0, "runs": 0, "sixes": 0}, "innings": {"id": "206970", "runRate": 0.66, "remainingBalls": 291, "byes": 0, "number": 1, "balls": 9, "noBalls": 0, "wickets": 1, "legByes": 0, "ballLimit": 300, "target": 0, "session": 1, "day": 1, "fallOfWickets": 1, "remainingOvers": 0.0, "totalRuns": 0, "wides": 0, "runs": 1}, "over": {"ball": 3, "balls": 6, "complete": false, "limit": 50.0, "maiden": 0, "noBall": 0, "wide": 0, "byes": 0, "legByes": 0, "number": 2, "runs": 1, "wickets": 1, "overs": 1.3, "actual": 1.3, "unique": 1.03}, "dismissal": {"dismissal": true, "bowled": true, "type": "caught", "bowler": {"athlete": {"id": "391485", "name": "Jason Holder", "shortName": "Holder", "fullName": "Jason Omar Holder", "displayName": "Jason Holder"}}, "batsman": {"athlete": {"id": "380354", "name": "Anamul Haque", "shortName": "Anamul", "fullName": "Mohammad Anamul Haque Bijoy", "displayName": "Anamul Haque"}}, "fielder": {"athlete": {}}, "minutes": 0, "retiredText": "", "text": "Anamul Haque c Nurse b Holder 0 (3b 0x4 0x6) SR: 0.00"}}, {"id": "11040", "clock": "00:00", "date": "2018-07-22T09:30", "playType": {"id": "2", "description": "no run"}, "team": {"id": "25", "name": "Bangladesh", "abbreviation": "BDESH", "displayName": "Bangladesh"}, "mediaId": 0, "period": 1, "periodText": "1st innings", "preText": "", "text": "full, angled across, pushed down the ground gently", "postText": "", "shortText": "Holder to Shakib Al Hasan, no run", "homeScore": "1/1", "awayScore": "0", "scoreValue": 0, "sequence": 100104, "athletesInvolved": [{"id": "391485", "name": "Jason Holder", "shortName": "Holder", "displayName": "Jason Holder"}, {"id": "56143", "name": "Shakib Al Hasan", "shortName": "Shakib", "displayName": "Shakib Al Hasan"}], "speedKPH": "", "speedMPH": "", "bowler": {"athlete": {"id": "391485", "name": "Jason Holder", "shortName": "Holder", "fullName": "Jason Omar Holder", "displayName": "Jason Holder"}, "team": {"id": "4", "name": "West Indies", "abbreviation": "WI", "displayName": "West Indies"}, "maidens": 0, "balls": 4, "wickets": 1, "overs": 0.4, "conceded": 0}, "otherBowler": {"athlete": {"id": "276298", "name": "Andre Russell", "shortName": "Russell", "fullName": "Andre Dwayne Russell", "displayName": "Andre Russell"}, "team": {"id": "4", "name": "West Indies", "abbreviation": "WI", "displayName": "West Indies"}, "maidens": 0, "balls": 6, "wickets": 0, "overs": 1.0, "conceded": 1}, "batsman": {"athlete": {"id": "56143", "name": "Shakib Al Hasan", "shortName": "Shakib", "fullName": "Shakib Al Hasan", "displayName": "Shakib Al Hasan"}, "team": {"id": "25", "name": "Bangladesh", "abbreviation": "BDESH", "displayName": "Bangladesh"}, "totalRuns": 0, "faced": 1, "fours": 0, "runs": 1, "sixes": 0}, "otherBatsman": {"athlete": {"id": "56194", "name": "Tamim Iqbal", "shortName": "Tamim", "fullName": "Tamim Iqbal Khan", "displayName": "Tamim Iqbal"}, "team": {"id": "25", "name": "Bangladesh", "abbreviation": "BDESH", "displayName": "Bangladesh"}, "totalRuns": 0, "faced": 6, "fours": 0, "runs": 0, "sixes": 0}, "innings": {"id": "206970", "runRate": 0.6, "remainingBalls": 290, "byes": 0, "number": 1, "balls": 10, "noBalls": 0, "wickets": 1, "legByes": 0, "ballLimit": 300, "target": 0, "session": 1, "day": 1, "fallOfWickets": 0, "remainingOvers": 0.0, "totalRuns": 0, "wides": 0, "runs": 1}, "over": {"ball": 4, "balls": 6, "complete": false, "limit": 50.0, "maiden": 0, "noBall": 0, "wide": 0, "byes": 0, "legByes": 0, "number": 2, "runs": 1, "wickets": 1, "overs": 1.4, "actual": 1.4, "unique": 1.04}, "dismissal": {"dismissal": false, "bowled": false, "type": "", "bowler": {"athlete": {"id": "391485", "name": "Jason Holder", "shortName": "Holder", "fullName": "Jason Omar Holder", "displayName": "Jason Holder"}}, "batsman": {"athlete": {"id": "56143", "name": "Shakib Al Hasan", "shortName": "Shakib", "fullName": "Shakib Al Hasan", "displayName": "Shakib Al Hasan"}}, "fielder": {"athlete": {}}, "minutes": 0, "retiredText": ""}}, {"id": "11050", "clock": "00:00", "date": "2018-07-22T09:30", "playType": {"id": "1", "description": "run"}, "team": {"id": "25", "name": "Bangladesh", "abbreviation": "BDESH", "displayName": "Bangladesh"}, "mediaId": 0, "period": 1, "periodText": "1st innings", "preText": "", "text": "full, angled across off, driven off the front foot past extra cover", "postText": "", "shortText": "Holder to Shakib Al Hasan, 1 run", "homeScore": "2/1", "awayScore": "0", "scoreValue": 1, "sequence": 100105, "athletesInvolved": [{"id": "391485", "name": "Jason Holder", "shortName": "Holder", "displayName": "Jason Holder"}, {"id": "56143", "name": "Shakib Al Hasan", "shortName": "Shakib", "displayName": "Shakib Al Hasan"}], "speedKPH": "", "speedMPH": "", "bowler": {"athlete": {"id": "391485", "name": "Jason Holder", "shortName": "Holder", "fullName": "Jason Omar Holder", "displayName": "Jason Holder"}, "team": {"id": "4", "name": "West Indies", "abbreviation": "WI", "displayName": "West Indies"}, "maidens": 0, "balls": 5, "wickets": 1, "overs": 0.5, "conceded": 1}, "otherBowler": {"athlete": {"id": "276298", "name": "Andre Russell", "shortName": "Russell", "fullName": "Andre Dwayne Russell", "displayName": "Andre Russell"}, "team": {"id": "4", "name": "West Indies", "abbreviation": "WI", "displayName": "West Indies"}, "maidens": 0, "balls": 6, "wickets": 0, "overs": 1.0, "conceded": 1}, "batsman": {"athlete": {"id": "56143", "name": "Shakib Al Hasan", "shortName": "Shakib", "fullName": "Shakib Al Hasan", "displayName": "Shakib Al Hasan"}, "team": {"id": "25", "name": "Bangladesh", "abbreviation": "BDESH", "displayName": "Bangladesh"}, "totalRuns": 1, "faced": 2, "fours": 0, "runs": 2, "sixes": 0}, "otherBatsman": {"athlete": {"id": "56194", "name": "Tamim Iqbal", "shortName": "Tamim", "fullName": "Tamim Iqbal Khan", "displayName": "Tamim Iqbal"}, "team": {"id": "25", "name": "Bangladesh", "abbreviation": "BDESH", "displayName": "Bangladesh"}, "totalRuns": 0, "faced": 6, "fours": 0, "runs": 0, "sixes": 0}, "innings": {"id": "206970", "runRate": 1.09, "remainingBalls": 289, "byes": 0, "number": 1, "balls": 11, "noBalls": 0, "wickets": 1, "legByes": 0, "ballLimit": 300, "target": 0, "session": 1, "day": 1, "fallOfWickets": 0, "remainingOvers": 0.0, "totalRuns": 1, "wides": 0, "runs": 2}, "over": {"ball": 5, "balls": 6, "complete": false, "limit": 50.0, "maiden": 0, "noBall": 0, "wide": 0, "byes": 0, "legByes": 0, "number": 2, "runs": 1, "wickets": 1, "overs": 1.5, "actual": 1.5, "unique": 1.05}, "dismissal": {"dismissal": false, "bowled": false, "type": "", "bowler": {"athlete": {"id": "391485", "name": "Jason Holder", "shortName": "Holder", "fullName": "Jason Omar Holder", "displayName": "Jason Holder"}}, "batsman": {"athlete": {"id": "56143", "name": "Shakib Al Hasan", "shortName": "Shakib", "fullName": "Shakib Al Hasan", "displayName": "Shakib Al Hasan"}}, "fielder": {"athlete": {}}, "minutes": 0, "retiredText": ""}}, {"id": "11060", "clock": "00:00", "date": "2018-07-22T09:30", "playType": {"id": "2", "description": "no run"}, "team": {"id": "25", "name": "Bangladesh", "abbreviation": "BDESH", "displayName": "Bangladesh"}, "mediaId": 0, "period": 1, "periodText": "1st innings", "preText": "", "text": "length ball that straightens from outside off, defended", "postText": "", "shortText": "Holder to Tamim Iqbal, no run", "homeScore": "2/1", "awayScore": "0", "scoreValue": 0, "sequence": 100106, "athletesInvolved": [{"id": "56194", "name": "Tamim Iqbal", "shortName": "Tamim", "displayName": "Tamim Iqbal"}, {"id": "391485", "name": "Jason Holder", "shortName": "Holder", "displayName": "Jason Holder"}], "speedKPH": "", "speedMPH": "", "bowler": {"athlete": {"id": "391485", "name": "Jason Holder", "shortName": "Holder", "fullName": "Jason Omar Holder", "displayName": "Jason Holder"}, "team": {"id": "4", "name": "West Indies", "abbreviation": "WI", "displayName": "West Indies"}, "maidens": 0, "balls": 6, "wickets": 1, "overs": 1.0, "conceded": 1}, "otherBowler": {"athlete": {"id": "276298", "name": "Andre Russell", "shortName": "Russell", "fullName": "Andre Dwayne Russell", "displayName": "Andre Russell"}, "team": {"id": "4", "name": "West Indies", "abbreviation": "WI", "displayName": "West Indies"}, "maidens": 0, "balls": 6, "wickets": 0, "overs": 1.0, "conceded": 1}, "batsman": {"athlete": {"id": "56194", "name": "Tamim Iqbal", "shortName": "Tamim", "fullName": "Tamim Iqbal Khan", "displayName": "Tamim Iqbal"}, "team": {"id": "25", "name": "Bangladesh", "abbreviation": "BDESH", "displayName": "Bangladesh"}, "totalRuns": 0, "faced": 7, "fours": 0, "runs": 2, "sixes": 0}, "otherBatsman": {"athlete": {"id": "56143", "name": "Shakib Al Hasan", "shortName": "Shakib", "fullName": "Shakib Al Hasan", "displayName": "Shakib Al Hasan"}, "team": {"id": "25", "name": "Bangladesh", "abbreviation": "BDESH", "displayName": "Bangladesh"}, "totalRuns": 1, "faced": 2, "fours": 0, "runs": 0, "sixes": 0}, "innings": {"id": "206970", "runRate": 1.0, "remainingBalls": 288, "byes": 0, "number": 1, "balls": 12, "noBalls": 0, "wickets": 1, "legByes": 0, "ballLimit": 300, "target": 0, "session": 1, "day": 1, "fallOfWickets": 0, "remainingOvers": 0.0, "totalRuns": 0, "wides": 0, "runs": 2}, "over": {"ball": 6, "balls": 6, "complete": true, "limit": 50.0, "maiden": 0, "noBall": 0, "wide": 0, "byes": 0, "legByes": 0, "number": 2, "runs": 1, "wickets": 1, "overs": 1.6, "actual": 1.6, "unique": 1.06}, "dismissal": {"dismissal": false, "bowled": false, "type": "", "bowler": {"athlete": {"id": "391485", "name": "Jason Holder", "shortName": "Holder", "fullName": "Jason Omar Holder", "displayName": "Jason Holder"}}, "batsman": {"athlete": {"id": "56194", "name": "Tamim Iqbal", "shortName": "Tamim", "fullName": "Tamim Iqbal Khan", "displayName": "Tamim Iqbal"}}, "fielder": {"athlete": {}}, "minutes": 0, "retiredText": ""}}, {"id": "12010", "clock": "00:00", "date": "2018-07-22T09:30", "playType": {"id": "1", "description": "run"}, "team": {"id": "25", "name": "Bangladesh", "abbreviation": "BDESH", "displayName": "Bangladesh"}, "mediaId": 0, "period": 1, "periodText": "1st innings", "preText": "", "text": "short of a length, tucked off the hips around the corner", "postText": "", "shortText": "Russell to Shakib Al Hasan, 1 run", "homeScore": "3/1", "awayScore": "0", "scoreValue": 1, "sequence": 100201, "athletesInvolved": [{"id": "276298", "name": "Andre Russell", "shortName": "Russell", "displayName": "Andre Russell"}, {"id": "56143", "name": "Shakib Al Hasan", "shortName": "Shakib", "displayName": "Shakib Al Hasan"}], "speedKPH": "", "speedMPH": "", "bowler": {"athlete": {"id": "276298", "name": "Andre Russell", "shortName": "Russell", "fullName": "Andre Dwayne Russell", "displayName": "Andre Russell"}, "team": {"id": "4", "name": "West Indies", "abbreviation": "WI", "displayName": "West Indies"}, "maidens": 0, "balls": 7, "wickets": 0, "overs": 1.1, "conceded": 2}, "otherBowler": {"athlete": {"id": "391485", "name": "Jason Holder", "shortName": "Holder", "fullName": "Jason Omar Holder", "displayName": "Jason Holder"}, "team": {"id": "4", "name": "West Indies", "abbreviation": "WI", "displayName": "West Indies"}, "maidens": 0, "balls": 6, "wickets": 1, "overs": 1.0, "conceded": 1}, "batsman": {"athlete": {"id": "56143", "name": "Shakib Al Hasan", "shortName": "Shakib", "fullName": "Shakib Al Hasan", "displayName": "Shakib Al Hasan"}, "team": {"id": "25", "name": "Bangladesh", "abbreviation": "BDESH", "displayName": "Bangladesh"}, "totalRuns": 2, "faced": 3, "fours": 0, "runs": 3, "sixes": 0}, "otherBatsman": {"athlete": {"id": "56194", "name": "Tamim Iqbal", "shortName": "Tamim", "fullName": "Tamim Iqbal Khan", "displayName": "Tamim Iqbal"}, "team": {"id": "25", "name": "Bangladesh", "abbreviation": "BDESH", "displayName": "Bangladesh"}, "totalRuns": 0, "faced": 7, "fours": 0, "runs": 0, "sixes": 0}, "innings": {"id": "206970", "runRate": 1.38, "remainingBalls": 287, "byes": 0, "number": 1, "balls": 13, "noBalls": 0, "wickets": 1, "legByes": 0, "ballLimit": 300, "target": 0, "session": 1, "day": 1, "fallOfWickets": 0, "remainingOvers": 0.0, "totalRuns": 1, "wides": 0, "runs": 3}, "over": {"ball": 1, "balls": 6, "complete": false, "limit": 50.0, "maiden": 0, "noBall": 0, "wide": 0, "byes": 0, "legByes": 0, "number": 3, "runs": 3, "wickets": 0, "overs": 2.1, "actual": 2.1, "unique": 2.01}, "dismissal": {"dismissal": false, "bowled": false, "type": "", "bowler": {"athlete": {"id": "276298", "name": "Andre Russell", "shortName": "Russell", "fullName": "Andre Dwayne Russell", "displayName": "Andre Russell"}}, "batsman": {"athlete": {"id": "56143", "name": "Shakib Al Hasan", "shortName": "Shakib", "fullName": "Shakib Al Hasan", "displayName": "Shakib Al Hasan"}}, "fielder": {"athlete": {}}, "minutes": 0, "retiredText": ""}}, {"id": "12020", "clock": "00:00", "date": "2018-07-22T09:30", "playType": {"id": "2", "description": "no run"}, "team": {"id": "25", "name": "Bangladesh", "abbreviation": "BDESH", "displayName": "Bangladesh"}, "mediaId": 0, "period": 1, "periodText": "1st innings", "preText": "Davo from GUYAN: \"Here's some local tip..... don't ever try predicting the weather in Guyana, we have a saying here..if you want rain, bring cricket...however, it rained heavily 3 days ago but since then we've had bright sunshine...trust me we won't get any rain today, the clouds usually build up here but the rain blows towards the western area.. i am GUYANESE.....also, i am here in the Green Stand applauding as the players walk out..\"", "text": "short, angled across, arches out of the way", "postText": "", "shortText": "Russell to Tamim Iqbal, no run", "homeScore": "3/1", "awayScore": "0", "scoreValue": 0, "sequence": 100202, "athletesInvolved": [{"id": "56194", "name": "Tamim Iqbal", "shortName": "Tamim", "displayName": "Tamim Iqbal"}, {"id": "276298", "name": "Andre Russell", "shortName": "Russell", "displayName": "Andre Russell"}], "speedKPH": "", "speedMPH": "", "bowler": {"athlete": {"id": "276298", "name": "Andre Russell", "shortName": "Russell", "fullName": "Andre Dwayne Russell", "displayName": "Andre Russell"}, "team": {"id": "4", "name": "West Indies", "abbreviation": "WI", "displayName": "West Indies"}, "maidens": 0, "balls": 8, "wickets": 0, "overs": 1.2, "conceded": 2}, "otherBowler": {"athlete": {"id": "391485", "name": "Jason Holder", "shortName": "Holder", "fullName": "Jason Omar Holder", "displayName": "Jason Holder"}, "team": {"id": "4", "name": "West Indies", "abbreviation": "WI", "displayName": "West Indies"}, "maidens": 0, "balls": 6, "wickets": 1, "overs": 1.0, "conceded": 1}, "batsman": {"athlete": {"id": "56194", "name": "Tamim Iqbal", "shortName": "Tamim", "fullName": "Tamim Iqbal Khan", "displayName": "Tamim Iqbal"}, "team": {"id": "25", "name": "Bangladesh", "abbreviation": "BDESH", "displayName": "Bangladesh"}, "totalRuns": 0, "faced": 8, "fours": 0, "runs": 3, "sixes": 0}, "otherBatsman": {"athlete": {"id": "56143", "name": "Shakib Al Hasan", "shortName": "Shakib", "fullName": "Shakib Al Hasan", "displayName": "Shakib Al Hasan"}, "team": {"id": "25", "name": "Bangladesh", "abbreviation": "BDESH", "displayName": "Bangladesh"}, "totalRuns": 2, "faced": 3, "fours": 0, "runs": 0, "sixes": 0}, "innings": {"id": "206970", "runRate": 1.28, "remainingBalls": 286, "byes": 0, "number": 1, "balls": 14, "noBalls": 0, "wickets": 1, "legByes": 0, "ballLimit": 300, "target": 0, "session": 1, "day": 1, "fallOfWickets": 0, "remainingOvers": 0.0, "totalRuns": 0, "wides": 0, "runs": 3}, "over": {"ball": 2, "balls": 6, "complete": false, "limit": 50.0, "maiden": 0, "noBall": 0, "wide": 0, "byes": 0, "legByes": 0, "number": 3, "runs": 3, "wickets": 0, "overs": 2.2, "actual": 2.2, "unique": 2.02}, "dismissal": {"dismissal": false, "bowled": false, "type": "", "bowler": {"athlete": {"id": "276298", "name": "Andre Russell", "shortName": "Russell", "fullName": "Andre Dwayne Russell", "displayName": "Andre Russell"}}, "batsman": {"athlete": {"id": "56194", "name": "Tamim Iqbal", "shortName": "Tamim", "fullName": "Tamim Iqbal Khan", "displayName": "Tamim Iqbal"}}, "fielder": {"athlete": {}}, "minutes": 0, "retiredText": ""}}, {"id": "12030", "clock": "00:00", "date": "2018-07-22T09:30", "playType": {"id": "2", "description": "no run"}, "team": {"id": "25", "name": "Bangladesh", "abbreviation": "BDESH", "displayName": "Bangladesh"}, "mediaId": 0, "period": 1, "periodText": "1st innings", "preText": "", "text": "short ball, tucks him up by banging it in around middle, and forces him to arch away", "postText": "", "shortText": "Russell to Tamim Iqbal, no run", "homeScore": "3/1", "awayScore": "0", "scoreValue": 0, "sequence": 100203, "athletesInvolved": [{"id": "56194", "name": "Tamim Iqbal", "shortName": "Tamim", "displayName": "Tamim Iqbal"}, {"id": "276298", "name": "Andre Russell", "shortName": "Russell", "displayName": "Andre Russell"}], "speedKPH": "", "speedMPH": "", "bowler": {"athlete": {"id": "276298", "name": "Andre Russell", "shortName": "Russell", "fullName": "Andre Dwayne Russell", "displayName": "Andre Russell"}, "team": {"id": "4", "name": "West Indies", "abbreviation": "WI", "displayName": "West Indies"}, "maidens": 0, "balls": 9, "wickets": 0, "overs": 1.3, "conceded": 2}, "otherBowler": {"athlete": {"id": "391485", "name": "Jason Holder", "shortName": "Holder", "fullName": "Jason Omar Holder", "displayName": "Jason Holder"}, "team": {"id": "4", "name": "West Indies", "abbreviation": "WI", "displayName": "West Indies"}, "maidens": 0, "balls": 6, "wickets": 1, "overs": 1.0, "conceded": 1}, "batsman": {"athlete": {"id": "56194", "name": "Tamim Iqbal", "shortName": "Tamim", "fullName": "Tamim Iqbal Khan", "displayName": "Tamim Iqbal"}, "team": {"id": "25", "name": "Bangladesh", "abbreviation": "BDESH", "displayName": "Bangladesh"}, "totalRuns": 0, "faced": 9, "fours": 0, "runs": 3, "sixes": 0}, "otherBatsman": {"athlete": {"id": "56143", "name": "Shakib Al Hasan", "shortName": "Shakib", "fullName": "Shakib Al Hasan", "displayName": "Shakib Al Hasan"}, "team": {"id": "25", "name": "Bangladesh", "abbreviation": "BDESH", "displayName": "Bangladesh"}, "totalRuns": 2, "faced": 3, "fours": 0, "runs": 0, "sixes": 0}, "innings": {"id": "206970", "runRate": 1.2, "remainingBalls": 285, "byes": 0, "number": 1, "balls": 15, "noBalls": 0, "wickets": 1, "legByes": 0, "ballLimit": 300, "target": 0, "session": 1, "day": 1, "fallOfWickets": 0, "remainingOvers": 0.0, "totalRuns": 0, "wides": 0, "runs": 3}, "over": {"ball": 3, "balls": 6, "complete": false, "limit": 50.0, "maiden": 0, "noBall": 0, "wide": 0, "byes": 0, "legByes": 0, "number": 3, "runs": 3, "wickets": 0, "overs": 2.3, "actual": 2.3, "unique": 2.03}, "dismissal": {"dismissal": false, "bowled": false, "type": "", "bowler": {"athlete": {"id": "276298", "name": "Andre Russell", "shortName": "Russell", "fullName": "Andre Dwayne Russell", "displayName": "Andre Russell"}}, "batsman": {"athlete": {"id": "56194", "name": "Tamim Iqbal", "shortName": "Tamim", "fullName": "Tamim Iqbal Khan", "displayName": "Tamim Iqbal"}}, "fielder": {"athlete": {}}, "minutes": 0, "retiredText": ""}}, {"id": "12040", "clock": "00:00", "date": "2018-07-22T09:30", "playType": {"id": "1", "description": "run"}, "team": {"id": "25", "name": "Bangladesh", "abbreviation": "BDESH", "displayName": "Bangladesh"}, "mediaId": 0, "period": 1, "periodText": "1st innings", "preText": "", "text": "short of good length, leg-stump line, tucked through square leg", "postText": "Groundstaff at the ready.", "shortText": "Russell to Tamim Iqbal, 2 runs", "homeScore": "5/1", "awayScore": "0", "scoreValue": 2, "sequence": 100204, "athletesInvolved": [{"id": "56194", "name": "Tamim Iqbal", "shortName": "Tamim", "displayName": "Tamim Iqbal"}, {"id": "276298", "name": "Andre Russell", "shortName": "Russell", "displayName": "Andre Russell"}], "speedKPH": "", "speedMPH": "", "bowler": {"athlete": {"id": "276298", "name": "Andre Russell", "shortName": "Russell", "fullName": "Andre Dwayne Russell", "displayName": "Andre Russell"}, "team": {"id": "4", "name": "West Indies", "abbreviation": "WI", "displayName": "West Indies"}, "maidens": 0, "balls": 10, "wickets": 0, "overs": 1.4, "conceded": 4}, "otherBowler": {"athlete": {"id": "391485", "name": "Jason Holder", "shortName": "Holder", "fullName": "Jason Omar Holder", "displayName": "Jason Holder"}, "team": {"id": "4", "name": "West Indies", "abbreviation": "WI", "displayName": "West Indies"}, "maidens": 0, "balls": 6, "wickets": 1, "overs": 1.0, "conceded": 1}, "batsman": {"athlete": {"id": "56194", "name": "Tamim Iqbal", "shortName": "Tamim", "fullName": "Tamim Iqbal Khan", "displayName": "Tamim Iqbal"}, "team": {"id": "25", "name": "Bangladesh", "abbreviation": "BDESH", "displayName": "Bangladesh"}, "totalRuns": 2, "faced": 10, "fours": 0, "runs": 5, "sixes": 0}, "otherBatsman": {"athlete": {"id": "56143", "name": "Shakib Al Hasan", "shortName": "Shakib", "fullName": "Shakib Al Hasan", "displayName": "Shakib Al Hasan"}, "team": {"id": "25", "name": "Bangladesh", "abbreviation": "BDESH", "displayName": "Bangladesh"}, "totalRuns": 2, "faced": 3, "fours": 0, "runs": 0, "sixes": 0}, "innings": {"id": "206970", "runRate": 1.87, "remainingBalls": 284, "byes": 0, "number": 1, "balls": 16, "noBalls": 0, "wickets": 1, "legByes": 0, "ballLimit": 300, "target": 0, "session": 1, "day": 1, "fallOfWickets": 0, "remainingOvers": 0.0, "totalRuns": 2, "wides": 0, "runs": 5}, "over": {"ball": 4, "balls": 6, "complete": false, "limit": 50.0, "maiden": 0, "noBall": 0, "wide": 0, "byes": 0, "legByes": 0, "number": 3, "runs": 3, "wickets": 0, "overs": 2.4, "actual": 2.4, "unique": 2.04}, "dismissal": {"dismissal": false, "bowled": false, "type": "", "bowler": {"athlete": {"id": "276298", "name": "Andre Russell", "shortName": "Russell", "fullName": "Andre Dwayne Russell", "displayName": "Andre Russell"}}, "batsman": {"athlete": {"id": "56194", "name": "Tamim Iqbal", "shortName": "Tamim", "fullName": "Tamim Iqbal Khan", "displayName": "Tamim Iqbal"}}, "fielder": {"athlete": {}}, "minutes": 0, "retiredText": ""}}, {"id": "12050", "clock": "00:00", "date": "2018-07-22T09:30", "playType": {"id": "2", "description": "no run"}, "team": {"id": "25", "name": "Bangladesh", "abbreviation": "BDESH", "displayName": "Bangladesh"}, "mediaId": 0, "period": 1, "periodText": "1st innings", "preText": "A mild drizzle has already begun. Just a drop or two on the camera lens.", "text": "length ball, gets opened up slightly as he blocks", "postText": "", "shortText": "Russell to Tamim Iqbal, no run", "homeScore": "5/1", "awayScore": "0", "scoreValue": 0, "sequence": 100205, "athletesInvolved": [{"id": "56194", "name": "Tamim Iqbal", "shortName": "Tamim", "displayName": "Tamim Iqbal"}, {"id": "276298", "name": "Andre Russell", "shortName": "Russell", "displayName": "Andre Russell"}], "speedKPH": "", "speedMPH": "", "bowler": {"athlete": {"id": "276298", "name": "Andre Russell", "shortName": "Russell", "fullName": "Andre Dwayne Russell", "displayName": "Andre Russell"}, "team": {"id": "4", "name": "West Indies", "abbreviation": "WI", "displayName": "West Indies"}, "maidens": 0, "balls": 11, "wickets": 0, "overs": 1.5, "conceded": 4}, "otherBowler": {"athlete": {"id": "391485", "name": "Jason Holder", "shortName": "Holder", "fullName": "Jason Omar Holder", "displayName": "Jason Holder"}, "team": {"id": "4", "name": "West Indies", "abbreviation": "WI", "displayName": "West Indies"}, "maidens": 0, "balls": 6, "wickets": 1, "overs": 1.0, "conceded": 1}, "batsman": {"athlete": {"id": "56194", "name": "Tamim Iqbal", "shortName": "Tamim", "fullName": "Tamim Iqbal Khan", "displayName": "Tamim Iqbal"}, "team": {"id": "25", "name": "Bangladesh", "abbreviation": "BDESH", "displayName": "Bangladesh"}, "totalRuns": 2, "faced": 11, "fours": 0, "runs": 5, "sixes": 0}, "otherBatsman": {"athlete": {"id": "56143", "name": "Shakib Al Hasan", "shortName": "Shakib", "fullName": "Shakib Al Hasan", "displayName": "Shakib Al Hasan"}, "team": {"id": "25", "name": "Bangladesh", "abbreviation": "BDESH", "displayName": "Bangladesh"}, "totalRuns": 2, "faced": 3, "fours": 0, "runs": 0, "sixes": 0}, "innings": {"id": "206970", "runRate": 1.76, "remainingBalls": 283, "byes": 0, "number": 1, "balls": 17, "noBalls": 0, "wickets": 1, "legByes": 0, "ballLimit": 300, "target": 0, "session": 1, "day": 1, "fallOfWickets": 0, "remainingOvers": 0.0, "totalRuns": 0, "wides": 0, "runs": 5}, "over": {"ball": 5, "balls": 6, "complete": false, "limit": 50.0, "maiden": 0, "noBall": 0, "wide": 0, "byes": 0, "legByes": 0, "number": 3, "runs": 3, "wickets": 0, "overs": 2.5, "actual": 2.5, "unique": 2.05}, "dismissal": {"dismissal": false, "bowled": false, "type": "", "bowler": {"athlete": {"id": "276298", "name": "Andre Russell", "shortName": "Russell", "fullName": "Andre Dwayne Russell", "displayName": "Andre Russell"}}, "batsman": {"athlete": {"id": "56194", "name": "Tamim Iqbal", "shortName": "Tamim", "fullName": "Tamim Iqbal Khan", "displayName": "Tamim Iqbal"}}, "fielder": {"athlete": {}}, "minutes": 0, "retiredText": ""}}, {"id": "12060", "clock": "00:00", "date": "2018-07-22T09:30", "playType": {"id": "2", "description": "no run"}, "team": {"id": "25", "name": "Bangladesh", "abbreviation": "BDESH", "displayName": "Bangladesh"}, "mediaId": 0, "period": 1, "periodText": "1st innings", "preText": "", "text": "good length on the fourth-stump line, left alone", "postText": "", "shortText": "Russell to Tamim Iqbal, no run", "homeScore": "5/1", "awayScore": "0", "scoreValue": 0, "sequence": 100206, "athletesInvolved": [{"id": "56194", "name": "Tamim Iqbal", "shortName": "Tamim", "displayName": "Tamim Iqbal"}, {"id": "276298", "name": "Andre Russell", "shortName": "Russell", "displayName": "Andre Russell"}], "speedKPH": "", "speedMPH": "", "bowler": {"athlete": {"id": "276298", "name": "Andre Russell", "shortName": "Russell", "fullName": "Andre Dwayne Russell", "displayName": "Andre Russell"}, "team": {"id": "4", "name": "West Indies", "abbreviation": "WI", "displayName": "West Indies"}, "maidens": 0, "balls": 12, "wickets": 0, "overs": 2.0, "conceded": 4}, "otherBowler": {"athlete": {"id": "391485", "name": "Jason Holder", "shortName": "Holder", "fullName": "Jason Omar Holder", "displayName": "Jason Holder"}, "team": {"id": "4", "name": "West Indies", "abbreviation": "WI", "displayName": "West Indies"}, "maidens": 0, "balls": 6, "wickets": 1, "overs": 1.0, "conceded": 1}, "batsman": {"athlete": {"id": "56194", "name": "Tamim Iqbal", "shortName": "Tamim", "fullName": "Tamim Iqbal Khan", "displayName": "Tamim Iqbal"}, "team": {"id": "25", "name": "Bangladesh", "abbreviation": "BDESH", "displayName": "Bangladesh"}, "totalRuns": 2, "faced": 12, "fours": 0, "runs": 5, "sixes": 0}, "otherBatsman": {"athlete": {"id": "56143", "name": "Shakib Al Hasan", "shortName": "Shakib", "fullName": "Shakib Al Hasan", "displayName": "Shakib Al Hasan"}, "team": {"id": "25", "name": "Bangladesh", "abbreviation": "BDESH", "displayName": "Bangladesh"}, "totalRuns": 2, "faced": 3, "fours": 0, "runs": 0, "sixes": 0}, "innings": {"id": "206970", "runRate": 1.66, "remainingBalls": 282, "byes": 0, "number": 1, "balls": 18, "noBalls": 0, "wickets": 1, "legByes": 0, "ballLimit": 300, "target": 0, "session": 1, "day": 1, "fallOfWickets": 0, "remainingOvers": 0.0, "totalRuns": 0, "wides": 0, "runs": 5}, "over": {"ball": 6, "balls": 6, "complete": true, "limit": 50.0, "maiden": 0, "noBall": 0, "wide": 0, "byes": 0, "legByes": 0, "number": 3, "runs": 3, "wickets": 0, "overs": 2.6, "actual": 2.6, "unique": 2.06}, "dismissal": {"dismissal": false, "bowled": false, "type": "", "bowler": {"athlete": {"id": "276298", "name": "Andre Russell", "shortName": "Russell", "fullName": "Andre Dwayne Russell", "displayName": "Andre Russell"}}, "batsman": {"athlete": {"id": "56194", "name": "Tamim Iqbal", "shortName": "Tamim", "fullName": "Tamim Iqbal Khan", "displayName": "Tamim Iqbal"}}, "fielder": {"athlete": {}}, "minutes": 0, "retiredText": ""}}, {"id": "13010", "clock": "00:00", "date": "2018-07-22T09:30", "playType": {"id": "2", "description": "no run"}, "team": {"id": "25", "name": "Bangladesh", "abbreviation": "BDESH", "displayName": "Bangladesh"}, "mediaId": 0, "period": 1, "periodText": "1st innings", "preText": "", "text": "almost walks into the shot as he feels for one that cuts in from outside off and nearly nicks it through", "postText": "", "shortText": "Holder to Shakib Al Hasan, no run", "homeScore": "5/1", "awayScore": "0", "scoreValue": 0, "sequence": 100301, "athletesInvolved": [{"id": "391485", "name": "Jason Holder", "shortName": "Holder", "displayName": "Jason Holder"}, {"id": "56143", "name": "Shakib Al Hasan", "shortName": "Shakib", "displayName": "Shakib Al Hasan"}], "speedKPH": "", "speedMPH": "", "bowler": {"athlete": {"id": "391485", "name": "Jason Holder", "shortName": "Holder", "fullName": "Jason Omar Holder", "displayName": "Jason Holder"}, "team": {"id": "4", "name": "West Indies", "abbreviation": "WI", "displayName": "West Indies"}, "maidens": 0, "balls": 7, "wickets": 1, "overs": 1.1, "conceded": 1}, "otherBowler": {"athlete": {"id": "276298", "name": "Andre Russell", "shortName": "Russell", "fullName": "Andre Dwayne Russell", "displayName": "Andre Russell"}, "team": {"id": "4", "name": "West Indies", "abbreviation": "WI", "displayName": "West Indies"}, "maidens": 0, "balls": 12, "wickets": 0, "overs": 2.0, "conceded": 4}, "batsman": {"athlete": {"id": "56143", "name": "Shakib Al Hasan", "shortName": "Shakib", "fullName": "Shakib Al Hasan", "displayName": "Shakib Al Hasan"}, "team": {"id": "25", "name": "Bangladesh", "abbreviation": "BDESH", "displayName": "Bangladesh"}, "totalRuns": 2, "faced": 4, "fours": 0, "runs": 5, "sixes": 0}, "otherBatsman": {"athlete": {"id": "56194", "name": "Tamim Iqbal", "shortName": "Tamim", "fullName": "Tamim Iqbal Khan", "displayName": "Tamim Iqbal"}, "team": {"id": "25", "name": "Bangladesh", "abbreviation": "BDESH", "displayName": "Bangladesh"}, "totalRuns": 2, "faced": 12, "fours": 0, "runs": 0, "sixes": 0}, "innings": {"id": "206970", "runRate": 1.57, "remainingBalls": 281, "byes": 0, "number": 1, "balls": 19, "noBalls": 0, "wickets": 1, "legByes": 0, "ballLimit": 300, "target": 0, "session": 1, "day": 1, "fallOfWickets": 0, "remainingOvers": 0.0, "totalRuns": 0, "wides": 0, "runs": 5}, "over": {"ball": 1, "balls": 6, "complete": false, "limit": 50.0, "maiden": 0, "noBall": 0, "wide": 0, "byes": 0, "legByes": 0, "number": 4, "runs": 3, "wickets": 0, "overs": 3.1, "actual": 3.1, "unique": 3.01}, "dismissal": {"dismissal": false, "bowled": false, "type": "", "bowler": {"athlete": {"id": "391485", "name": "Jason Holder", "shortName": "Holder", "fullName": "Jason Omar Holder", "displayName": "Jason Holder"}}, "batsman": {"athlete": {"id": "56143", "name": "Shakib Al Hasan", "shortName": "Shakib", "fullName": "Shakib Al Hasan", "displayName": "Shakib Al Hasan"}}, "fielder": {"athlete": {}}, "minutes": 0, "retiredText": ""}}, {"id": "13020", "clock": "00:00", "date": "2018-07-22T09:30", "playType": {"id": "1", "description": "run"}, "team": {"id": "25", "name": "Bangladesh", "abbreviation": "BDESH", "displayName": "Bangladesh"}, "mediaId": 0, "period": 1, "periodText": "1st innings", "preText": "Drizzle has picked up. We should be away any moment now.", "text": "full, strides across to meet the pitch and pushes through the covers", "postText": "", "shortText": "Holder to Shakib Al Hasan, 2 runs", "homeScore": "7/1", "awayScore": "0", "scoreValue": 2, "sequence": 100302, "athletesInvolved": [{"id": "391485", "name": "Jason Holder", "shortName": "Holder", "displayName": "Jason Holder"}, {"id": "56143", "name": "Shakib Al Hasan", "shortName": "Shakib", "displayName": "Shakib Al Hasan"}], "speedKPH": "", "speedMPH": "", "bowler": {"athlete": {"id": "391485", "name": "Jason Holder", "shortName": "Holder", "fullName": "Jason Omar Holder", "displayName": "Jason Holder"}, "team": {"id": "4", "name": "West Indies", "abbreviation": "WI", "displayName": "West Indies"}, "maidens": 0, "balls": 8, "wickets": 1, "overs": 1.2, "conceded": 3}, "otherBowler": {"athlete": {"id": "276298", "name": "Andre Russell", "shortName": "Russell", "fullName": "Andre Dwayne Russell", "displayName": "Andre Russell"}, "team": {"id": "4", "name": "West Indies", "abbreviation": "WI", "displayName": "West Indies"}, "maidens": 0, "balls": 12, "wickets": 0, "overs": 2.0, "conceded": 4}, "batsman": {"athlete": {"id": "56143", "name": "Shakib Al Hasan", "shortName": "Shakib", "fullName": "Shakib Al Hasan", "displayName": "Shakib Al Hasan"}, "team": {"id": "25", "name": "Bangladesh", "abbreviation": "BDESH", "displayName": "Bangladesh"}, "totalRuns": 4, "faced": 5, "fours": 0, "runs": 7, "sixes": 0}, "otherBatsman": {"athlete": {"id": "56194", "name": "Tamim Iqbal", "shortName": "Tamim", "fullName": "Tamim Iqbal Khan", "displayName": "Tamim Iqbal"}, "team": {"id": "25", "name": "Bangladesh", "abbreviation": "BDESH", "displayName": "Bangladesh"}, "totalRuns": 2, "faced": 12, "fours": 0, "runs": 0, "sixes": 0}, "innings": {"id": "206970", "runRate": 2.1, "remainingBalls": 280, "byes": 0, "number": 1, "balls": 20, "noBalls": 0, "wickets": 1, "legByes": 0, "ballLimit": 300, "target": 0, "session": 1, "day": 1, "fallOfWickets": 0, "remainingOvers": 0.0, "totalRuns": 2, "wides": 0, "runs": 7}, "over": {"ball": 2, "balls": 6, "complete": false, "limit": 50.0, "maiden": 0, "noBall": 0, "wide": 0, "byes": 0, "legByes": 0, "number": 4, "runs": 3, "wickets": 0, "overs": 3.2, "actual": 3.2, "unique": 3.02}, "dismissal": {"dismissal": false, "bowled": false, "type": "", "bowler": {"athlete": {"id": "391485", "name": "Jason Holder", "shortName": "Holder", "fullName": "Jason Omar Holder", "displayName": "Jason Holder"}}, "batsman": {"athlete": {"id": "56143", "name": "Shakib Al Hasan", "shortName": "Shakib", "fullName": "Shakib Al Hasan", "displayName": "Shakib Al Hasan"}}, "fielder": {"athlete": {}}, "minutes": 0, "retiredText": ""}}, {"id": "13030", "clock": "00:00", "date": "2018-07-22T09:30", "playType": {"id": "2", "description": "no run"}, "team": {"id": "25", "name": "Bangladesh", "abbreviation": "BDESH", "displayName": "Bangladesh"}, "mediaId": 0, "period": 1, "periodText": "1st innings", "preText": "", "text": "chases a wide length ball and miscues it off the toe-end to mid-off", "postText": "", "shortText": "Holder to Shakib Al Hasan, no run", "homeScore": "7/1", "awayScore": "0", "scoreValue": 0, "sequence": 100303, "athletesInvolved": [{"id": "391485", "name": "Jason Holder", "shortName": "Holder", "displayName": "Jason Holder"}, {"id": "56143", "name": "Shakib Al Hasan", "shortName": "Shakib", "displayName": "Shakib Al Hasan"}], "speedKPH": "", "speedMPH": "", "bowler": {"athlete": {"id": "391485", "name": "Jason Holder", "shortName": "Holder", "fullName": "Jason Omar Holder", "displayName": "Jason Holder"}, "team": {"id": "4", "name": "West Indies", "abbreviation": "WI", "displayName": "West Indies"}, "maidens": 0, "balls": 9, "wickets": 1, "overs": 1.3, "conceded": 3}, "otherBowler": {"athlete": {"id": "276298", "name": "Andre Russell", "shortName": "Russell", "fullName": "Andre Dwayne Russell", "displayName": "Andre Russell"}, "team": {"id": "4", "name": "West Indies", "abbreviation": "WI", "displayName": "West Indies"}, "maidens": 0, "balls": 12, "wickets": 0, "overs": 2.0, "conceded": 4}, "batsman": {"athlete": {"id": "56143", "name": "Shakib Al Hasan", "shortName": "Shakib", "fullName": "Shakib Al Hasan", "displayName": "Shakib Al Hasan"}, "team": {"id": "25", "name": "Bangladesh", "abbreviation": "BDESH", "displayName": "Bangladesh"}, "totalRuns": 4, "faced": 6, "fours": 0, "runs": 7, "sixes": 0}, "otherBatsman": {"athlete": {"id": "56194", "name": "Tamim Iqbal", "shortName": "Tamim", "fullName": "Tamim Iqbal Khan", "displayName": "Tamim Iqbal"}, "team": {"id": "25", "name": "Bangladesh", "abbreviation": "BDESH", "displayName": "Bangladesh"}, "totalRuns": 2, "faced": 12, "fours": 0, "runs": 0, "sixes": 0}, "innings": {"id": "206970", "runRate": 2.0, "remainingBalls": 279, "byes": 0, "number": 1, "balls": 21, "noBalls": 0, "wickets": 1, "legByes": 0, "ballLimit": 300, "target": 0, "session": 1, "day": 1, "fallOfWickets": 0, "remainingOvers": 0.0, "totalRuns": 0, "wides": 0, "runs": 7}, "over": {"ball": 3, "balls": 6, "complete": false, "limit": 50.0, "maiden": 0, "noBall": 0, "wide": 0, "byes": 0, "legByes": 0, "number": 4, "runs": 3, "wickets": 0, "overs": 3.3, "actual": 3.3, "unique": 3.03}, "dismissal": {"dismissal": false, "bowled": false, "type": "", "bowler": {"athlete": {"id": "391485", "name": "Jason Holder", "shortName": "Holder", "fullName": "Jason Omar Holder", "displayName": "Jason Holder"}}, "batsman": {"athlete": {"id": "56143", "name": "Shakib Al Hasan", "shortName": "Shakib", "fullName": "Shakib Al Hasan", "displayName": "Shakib Al Hasan"}}, "fielder": {"athlete": {}}, "minutes": 0, "retiredText": ""}}, {"id": "13040", "clock": "00:00", "date": "2018-07-22T09:30", "playType": {"id": "1", "description": "run"}, "team": {"id": "25", "name": "Bangladesh", "abbreviation": "BDESH", "displayName": "Bangladesh"}, "mediaId": 0, "period": 1, "periodText": "1st innings", "preText": "", "text": "length outside off, crisply carves it away to backward point who flings himself to his left to cut it off", "postText": "", "shortText": "Holder to Shakib Al Hasan, 1 run", "homeScore": "8/1", "awayScore": "0", "scoreValue": 1, "sequence": 100304, "athletesInvolved": [{"id": "391485", "name": "Jason Holder", "shortName": "Holder", "displayName": "Jason Holder"}, {"id": "56143", "name": "Shakib Al Hasan", "shortName": "Shakib", "displayName": "Shakib Al Hasan"}], "speedKPH": "", "speedMPH": "", "bowler": {"athlete": {"id": "391485", "name": "Jason Holder", "shortName": "Holder", "fullName": "Jason Omar Holder", "displayName": "Jason Holder"}, "team": {"id": "4", "name": "West Indies", "abbreviation": "WI", "displayName": "West Indies"}, "maidens": 0, "balls": 10, "wickets": 1, "overs": 1.4, "conceded": 4}, "otherBowler": {"athlete": {"id": "276298", "name": "Andre Russell", "shortName": "Russell", "fullName": "Andre Dwayne Russell", "displayName": "Andre Russell"}, "team": {"id": "4", "name": "West Indies", "abbreviation": "WI", "displayName": "West Indies"}, "maidens": 0, "balls": 12, "wickets": 0, "overs": 2.0, "conceded": 4}, "batsman": {"athlete": {"id": "56143", "name": "Shakib Al Hasan", "shortName": "Shakib", "fullName": "Shakib Al Hasan", "displayName": "Shakib Al Hasan"}, "team": {"id": "25", "name": "Bangladesh", "abbreviation": "BDESH", "displayName": "Bangladesh"}, "totalRuns": 5, "faced": 7, "fours": 0, "runs": 8, "sixes": 0}, "otherBatsman": {"athlete": {"id": "56194", "name": "Tamim Iqbal", "shortName": "Tamim", "fullName": "Tamim Iqbal Khan", "displayName": "Tamim Iqbal"}, "team": {"id": "25", "name": "Bangladesh", "abbreviation": "BDESH", "displayName": "Bangladesh"}, "totalRuns": 2, "faced": 12, "fours": 0, "runs": 0, "sixes": 0}, "innings": {"id": "206970", "runRate": 2.18, "remainingBalls": 278, "byes": 0, "number": 1, "balls": 22, "noBalls": 0, "wickets": 1, "legByes": 0, "ballLimit": 300, "target": 0, "session": 1, "day": 1, "fallOfWickets": 0, "remainingOvers": 0.0, "totalRuns": 1, "wides": 0, "runs": 8}, "over": {"ball": 4, "balls": 6, "complete": false, "limit": 50.0, "maiden": 0, "noBall": 0, "wide": 0, "byes": 0, "legByes": 0, "number": 4, "runs": 3, "wickets": 0, "overs": 3.4, "actual": 3.4, "unique": 3.04}, "dismissal": {"dismissal": false, "bowled": false, "type": "", "bowler": {"athlete": {"id": "391485", "name": "Jason Holder", "shortName": "Holder", "fullName": "Jason Omar Holder", "displayName": "Jason Holder"}}, "batsman": {"athlete": {"id": "56143", "name": "Shakib Al Hasan", "shortName": "Shakib", "fullName": "Shakib Al Hasan", "displayName": "Shakib Al Hasan"}}, "fielder": {"athlete": {}}, "minutes": 0, "retiredText": ""}}, {"id": "13050", "clock": "00:00", "date": "2018-07-22T09:30", "playType": {"id": "2", "description": "no run"}, "team": {"id": "25", "name": "Bangladesh", "abbreviation": "BDESH", "displayName": "Bangladesh"}, "mediaId": 0, "period": 1, "periodText": "1st innings", "preText": "", "text": "full, left alone outside off", "postText": "", "shortText": "Holder to Tamim Iqbal, no run", "homeScore": "8/1", "awayScore": "0", "scoreValue": 0, "sequence": 100305, "athletesInvolved": [{"id": "56194", "name": "Tamim Iqbal", "shortName": "Tamim", "displayName": "Tamim Iqbal"}, {"id": "391485", "name": "Jason Holder", "shortName": "Holder", "displayName": "Jason Holder"}], "speedKPH": "", "speedMPH": "", "bowler": {"athlete": {"id": "391485", "name": "Jason Holder", "shortName": "Holder", "fullName": "Jason Omar Holder", "displayName": "Jason Holder"}, "team": {"id": "4", "name": "West Indies", "abbreviation": "WI", "displayName": "West Indies"}, "maidens": 0, "balls": 11, "wickets": 1, "overs": 1.5, "conceded": 4}, "otherBowler": {"athlete": {"id": "276298", "name": "Andre Russell", "shortName": "Russell", "fullName": "Andre Dwayne Russell", "displayName": "Andre Russell"}, "team": {"id": "4", "name": "West Indies", "abbreviation": "WI", "displayName": "West Indies"}, "maidens": 0, "balls": 12, "wickets": 0, "overs": 2.0, "conceded": 4}, "batsman": {"athlete": {"id": "56194", "name": "Tamim Iqbal", "shortName": "Tamim", "fullName": "Tamim Iqbal Khan", "displayName": "Tamim Iqbal"}, "team": {"id": "25", "name": "Bangladesh", "abbreviation": "BDESH", "displayName": "Bangladesh"}, "totalRuns": 2, "faced": 13, "fours": 0, "runs": 8, "sixes": 0}, "otherBatsman": {"athlete": {"id": "56143", "name": "Shakib Al Hasan", "shortName": "Shakib", "fullName": "Shakib Al Hasan", "displayName": "Shakib Al Hasan"}, "team": {"id": "25", "name": "Bangladesh", "abbreviation": "BDESH", "displayName": "Bangladesh"}, "totalRuns": 5, "faced": 7, "fours": 0, "runs": 0, "sixes": 0}, "innings": {"id": "206970", "runRate": 2.08, "remainingBalls": 277, "byes": 0, "number": 1, "balls": 23, "noBalls": 0, "wickets": 1, "legByes": 0, "ballLimit": 300, "target": 0, "session": 1, "day": 1, "fallOfWickets": 0, "remainingOvers": 0.0, "totalRuns": 0, "wides": 0, "runs": 8}, "over": {"ball": 5, "balls": 6, "complete": false, "limit": 50.0, "maiden": 0, "noBall": 0, "wide": 0, "byes": 0, "legByes": 0, "number": 4, "runs": 3, "wickets": 0, "overs": 3.5, "actual": 3.5, "unique": 3.05}, "dismissal": {"dismissal": false, "bowled": false, "type": "", "bowler": {"athlete": {"id": "391485", "name": "Jason Holder", "shortName": "Holder", "fullName": "Jason Omar Holder", "displayName": "Jason Holder"}}, "batsman": {"athlete": {"id": "56194", "name": "Tamim Iqbal", "shortName": "Tamim", "fullName": "Tamim Iqbal Khan", "displayName": "Tamim Iqbal"}}, "fielder": {"athlete": {}}, "minutes": 0, "retiredText": ""}}, {"id": "13060", "clock": "00:00", "date": "2018-07-22T09:30", "playType": {"id": "2", "description": "no run"}, "team": {"id": "25", "name": "Bangladesh", "abbreviation": "BDESH", "displayName": "Bangladesh"}, "mediaId": 0, "period": 1, "periodText": "1st innings", "preText": "", "text": "advances down the ground but Holder takes it away from him and he's forced to let it go", "postText": "", "shortText": "Holder to Tamim Iqbal, no run", "homeScore": "8/1", "awayScore": "0", "scoreValue": 0, "sequence": 100306, "athletesInvolved": [{"id": "56194", "name": "Tamim Iqbal", "shortName": "Tamim", "displayName": "Tamim Iqbal"}, {"id": "391485", "name": "Jason Holder", "shortName": "Holder", "displayName": "Jason Holder"}], "speedKPH": "", "speedMPH": "", "bowler": {"athlete": {"id": "391485", "name": "Jason Holder", "shortName": "Holder", "fullName": "Jason Omar Holder", "displayName": "Jason Holder"}, "team": {"id": "4", "name": "West Indies", "abbreviation": "WI", "displayName": "West Indies"}, "maidens": 0, "balls": 12, "wickets": 1, "overs": 2.0, "conceded": 4}, "otherBowler": {"athlete": {"id": "276298", "name": "Andre Russell", "shortName": "Russell", "fullName": "Andre Dwayne Russell", "displayName": "Andre Russell"}, "team": {"id": "4", "name": "West Indies", "abbreviation": "WI", "displayName": "West Indies"}, "maidens": 0, "balls": 12, "wickets": 0, "overs": 2.0, "conceded": 4}, "batsman": {"athlete": {"id": "56194", "name": "Tamim Iqbal", "shortName": "Tamim", "fullName": "Tamim Iqbal Khan", "displayName": "Tamim Iqbal"}, "team": {"id": "25", "name": "Bangladesh", "abbreviation": "BDESH", "displayName": "Bangladesh"}, "totalRuns": 2, "faced": 14, "fours": 0, "runs": 8, "sixes": 0}, "otherBatsman": {"athlete": {"id": "56143", "name": "Shakib Al Hasan", "shortName": "Shakib", "fullName": "Shakib Al Hasan", "displayName": "Shakib Al Hasan"}, "team": {"id": "25", "name": "Bangladesh", "abbreviation": "BDESH", "displayName": "Bangladesh"}, "totalRuns": 5, "faced": 7, "fours": 0, "runs": 0, "sixes": 0}, "innings": {"id": "206970", "runRate": 2.0, "remainingBalls": 276, "byes": 0, "number": 1, "balls": 24, "noBalls": 0, "wickets": 1, "legByes": 0, "ballLimit": 300, "target": 0, "session": 1, "day": 1, "fallOfWickets": 0, "remainingOvers": 0.0, "totalRuns": 0, "wides": 0, "runs": 8}, "over": {"ball": 6, "balls": 6, "complete": true, "limit": 50.0, "maiden": 0, "noBall": 0, "wide": 0, "byes": 0, "legByes": 0, "number": 4, "runs": 3, "wickets": 0, "overs": 3.6, "actual": 3.6, "unique": 3.06}, "dismissal": {"dismissal": false, "bowled": false, "type": "", "bowler": {"athlete": {"id": "391485", "name": "Jason Holder", "shortName": "Holder", "fullName": "Jason Omar Holder", "displayName": "Jason Holder"}}, "batsman": {"athlete": {"id": "56194", "name": "Tamim Iqbal", "shortName": "Tamim", "fullName": "Tamim Iqbal Khan", "displayName": "Tamim Iqbal"}}, "fielder": {"athlete": {}}, "minutes": 0, "retiredText": ""}}]}}