{"commentary": {"count": 307, "pageIndex": 11, "pageSize": 25, "pageCount": 13, "items": [{"id": "140040", "clock": "00:00", "date": "2018-01-19T12:00", "playType": {"id": "2", "description": "no run"}, "team": {"id": "25", "name": "Bangladesh", "abbreviation": "BDESH", "displayName": "Bangladesh"}, "mediaId": 0, "period": 1, "periodText": "1st innings", "preText": "", "text": "full but enough time to turn away, pushed into the off side", "postText": "", "shortText": "de Silva to Mahmudullah, no run", "homeScore": "244/3", "awayScore": "0", "scoreValue": 0, "sequence": 104004, "athletesInvolved": [{"id": "784379", "name": "Wanindu Hasaranga", "shortName": "de Silva", "displayName": "Wanindu Hasaranga"}, {"id": "56025", "name": "Mahmudullah", "shortName": "Mahmudullah", "displayName": "Mahmudullah"}], "speedKPH": "", "speedMPH": "", "bowler": {"athlete": {"id": "784379", "name": "Wanindu Hasaranga", "shortName": "de Silva", "fullName": "Pinnaduwage Wanindu Hasaranga de Silva", "displayName": "Wanindu Hasaranga"}, "team": {"id": "8", "name": "Sri Lanka", "abbreviation": "SL", "displayName": "Sri Lanka"}, "maidens": 0, "balls": 28, "wickets": 0, "overs": 4.4, "conceded": 33}, "otherBowler": {"athlete": {"id": "360456", "name": "Asela Gunaratne", "shortName": "Gunaratne", "fullName": "Downdegedara Asela Sampath Gunaratne", "displayName": "Asela Gunaratne"}, "team": {"id": "8", "name": "Sri Lanka", "abbreviation": "SL", "displayName": "Sri Lanka"}, "maidens": 0, "balls": 30, "wickets": 1, "overs": 5.0, "conceded": 38}, "batsman": {"athlete": {"id": "56025", "name": "Mahmudullah", "shortName": "Mahmudullah", "fullName": "Mohammad Mahmudullah", "displayName": "Mahmudullah"}, "team": {"id": "25", "name": "Bangladesh", "abbreviation": "BDESH", "displayName": "Bangladesh"}, "totalRuns": 7, "faced": 8, "fours": 1, "runs": 244, "sixes": 0}, "otherBatsman": {"athlete": {"id": "56029", "name": "Mushfiqur Rahim", "shortName": "Mushfiqur", "fullName": "Mohammad Mushfiqur Rahim", "displayName": "Mushfiqur Rahim"}, "team": {"id": "25", "name": "Bangladesh", "abbreviation": "BDESH", "displayName": "Bangladesh"}, "totalRuns": 40, "faced": 34, "fours": 2, "runs": 0, "sixes": 1}, "innings": {"id": "202064", "runRate": 6.0, "remainingBalls": 56, "byes": 0, "number": 1, "balls": 244, "noBalls": 0, "wickets": 3, "legByes": 0, "ballLimit": 300, "target": 0, "session": 1, "day": 1, "fallOfWickets": 0, "remainingOvers": 0.0, "totalRuns": 0, "wides": 0, "runs": 244}, "over": {"ball": 4, "balls": 6, "complete": false, "limit": 50.0, "maiden": 0, "noBall": 0, "wide": 0, "byes": 0, "legByes": 0, "number": 41, "runs": 3, "wickets": 0, "overs": 40.4, "actual": 40.4, "unique": 40.04}, "dismissal": {"dismissal": false, "bowled": false, "type": "", "bowler": {"athlete": {"id": "784379", "name": "Wanindu Hasaranga", "shortName": "de Silva", "fullName": "Pinnaduwage Wanindu Hasaranga de Silva", "displayName": "Wanindu Hasaranga"}}, "batsman": {"athlete": {"id": "56025", "name": "Mahmudullah", "shortName": "Mahmudullah", "fullName": "Mohammad Mahmudullah", "displayName": "Mahmudullah"}}, "fielder": {"athlete": {}}, "minutes": 0, "retiredText": ""}}, {"id": "140050", "clock": "00:00", "date": "2018-01-19T12:00", "playType": {"id": "1", "description": "run"}, "team": {"id": "25", "name": "Bangladesh", "abbreviation": "BDESH", "displayName": "Bangladesh"}, "mediaId": 0, "period": 1, "periodText": "1st innings", "preText": "", "text": "<b>shouts of catch but in front of long-off</b>. Turns away and messes up his lofted stroke as he chips it off the outside of the bat", "postText": "", "shortText": "de Silva to Mahmudullah, 1 run", "homeScore": "245/3", "awayScore": "0", "scoreValue": 1, "sequence": 104005, "athletesInvolved": [{"id": "784379", "name": "Wanindu Hasaranga", "shortName": "de Silva", "displayName": "Wanindu Hasaranga"}, {"id": "56025", "name": "Mahmudullah", "shortName": "Mahmudullah", "displayName": "Mahmudullah"}], "speedKPH": "", "speedMPH": "", "bowler": {"athlete": {"id": "784379", "name": "Wanindu Hasaranga", "shortName": "de Silva", "fullName": "Pinnaduwage Wanindu Hasaranga de Silva", "displayName": "Wanindu Hasaranga"}, "team": {"id": "8", "name": "Sri Lanka", "abbreviation": "SL", "displayName": "Sri Lanka"}, "maidens": 0, "balls": 29, "wickets": 0, "overs": 4.5, "conceded": 34}, "otherBowler": {"athlete": {"id": "360456", "name": "Asela Gunaratne", "shortName": "Gunaratne", "fullName": "Downdegedara Asela Sampath Gunaratne", "displayName": "Asela Gunaratne"}, "team": {"id": "8", "name": "Sri Lanka", "abbreviation": "SL", "displayName": "Sri Lanka"}, "maidens": 0, "balls": 30, "wickets": 1, "overs": 5.0, "conceded": 38}, "batsman": {"athlete": {"id": "56025", "name": "Mahmudullah", "shortName": "Mahmudullah", "fullName": "Mohammad Mahmudullah", "displayName": "Mahmudullah"}, "team": {"id": "25", "name": "Bangladesh", "abbreviation": "BDESH", "displayName": "Bangladesh"}, "totalRuns": 8, "faced": 9, "fours": 1, "runs": 245, "sixes": 0}, "otherBatsman": {"athlete": {"id": "56029", "name": "Mushfiqur Rahim", "shortName": "Mushfiqur", "fullName": "Mohammad Mushfiqur Rahim", "displayName": "Mushfiqur Rahim"}, "team": {"id": "25", "name": "Bangladesh", "abbreviation": "BDESH", "displayName": "Bangladesh"}, "totalRuns": 40, "faced": 34, "fours": 2, "runs": 0, "sixes": 1}, "innings": {"id": "202064", "runRate": 6.0, "remainingBalls": 55, "byes": 0, "number": 1, "balls": 245, "noBalls": 0, "wickets": 3, "legByes": 0, "ballLimit": 300, "target": 0, "session": 1, "day": 1, "fallOfWickets": 0, "remainingOvers": 0.0, "totalRuns": 1, "wides": 0, "runs": 245}, "over": {"ball": 5, "balls": 6, "complete": false, "limit": 50.0, "maiden": 0, "noBall": 0, "wide": 0, "byes": 0, "legByes": 0, "number": 41, "runs": 3, "wickets": 0, "overs": 40.5, "actual": 40.5, "unique": 40.05}, "dismissal": {"dismissal": false, "bowled": false, "type": "", "bowler": {"athlete": {"id": "784379", "name": "Wanindu Hasaranga", "shortName": "de Silva", "fullName": "Pinnaduwage Wanindu Hasaranga de Silva", "displayName": "Wanindu Hasaranga"}}, "batsman": {"athlete": {"id": "56025", "name": "Mahmudullah", "shortName": "Mahmudullah", "fullName": "Mohammad Mahmudullah", "displayName": "Mahmudullah"}}, "fielder": {"athlete": {}}, "minutes": 0, "retiredText": ""}}, {"id": "140060", "clock": "00:00", "date": "2018-01-19T12:00", "playType": {"id": "1", "description": "run"}, "team": {"id": "25", "name": "Bangladesh", "abbreviation": "BDESH", "displayName": "Bangladesh"}, "mediaId": 0, "period": 1, "periodText": "1st innings", "preText": "", "text": "short and wide, cut to sweeper cover", "postText": "", "shortText": "de Silva to Mushfiqur Rahim, 1 run", "homeScore": "246/3", "awayScore": "0", "scoreValue": 1, "sequence": 104006, "athletesInvolved": [{"id": "784379", "name": "Wanindu Hasaranga", "shortName": "de Silva", "displayName": "Wanindu Hasaranga"}, {"id": "56029", "name": "Mushfiqur Rahim", "shortName": "Mushfiqur", "displayName": "Mushfiqur Rahim"}], "speedKPH": "", "speedMPH": "", "bowler": {"athlete": {"id": "784379", "name": "Wanindu Hasaranga", "shortName": "de Silva", "fullName": "Pinnaduwage Wanindu Hasaranga de Silva", "displayName": "Wanindu Hasaranga"}, "team": {"id": "8", "name": "Sri Lanka", "abbreviation": "SL", "displayName": "Sri Lanka"}, "maidens": 0, "balls": 30, "wickets": 0, "overs": 5.0, "conceded": 35}, "otherBowler": {"athlete": {"id": "360456", "name": "Asela Gunaratne", "shortName": "Gunaratne", "fullName": "Downdegedara Asela Sampath Gunaratne", "displayName": "Asela Gunaratne"}, "team": {"id": "8", "name": "Sri Lanka", "abbreviation": "SL", "displayName": "Sri Lanka"}, "maidens": 0, "balls": 30, "wickets": 1, "overs": 5.0, "conceded": 38}, "batsman": {"athlete": {"id": "56029", "name": "Mushfiqur Rahim", "shortName": "Mushfiqur", "fullName": "Mohammad Mushfiqur Rahim", "displayName": "Mushfiqur Rahim"}, "team": {"id": "25", "name": "Bangladesh", "abbreviation": "BDESH", "displayName": "Bangladesh"}, "totalRuns": 41, "faced": 35, "fours": 2, "runs": 246, "sixes": 1}, "otherBatsman": {"athlete": {"id": "56025", "name": "Mahmudullah", "shortName": "Mahmudullah", "fullName": "Mohammad Mahmudullah", "displayName": "Mahmudullah"}, "team": {"id": "25", "name": "Bangladesh", "abbreviation": "BDESH", "displayName": "Bangladesh"}, "totalRuns": 8, "faced": 9, "fours": 1, "runs": 0, "sixes": 0}, "innings": {"id": "202064", "runRate": 6.0, "remainingBalls": 54, "byes": 0, "number": 1, "balls": 246, "noBalls": 0, "wickets": 3, "legByes": 0, "ballLimit": 300, "target": 0, "session": 1, "day": 1, "fallOfWickets": 0, "remainingOvers": 0.0, "totalRuns": 1, "wides": 0, "runs": 246}, "over": {"ball": 6, "balls": 6, "complete": true, "limit": 50.0, "maiden": 0, "noBall": 0, "wide": 0, "byes": 0, "legByes": 0, "number": 41, "runs": 3, "wickets": 0, "overs": 40.6, "actual": 40.6, "unique": 40.06}, "dismissal": {"dismissal": false, "bowled": false, "type": "", "bowler": {"athlete": {"id": "784379", "name": "Wanindu Hasaranga", "shortName": "de Silva", "fullName": "Pinnaduwage Wanindu Hasaranga de Silva", "displayName": "Wanindu Hasaranga"}}, "batsman": {"athlete": {"id": "56029", "name": "Mushfiqur Rahim", "shortName": "Mushfiqur", "fullName": "Mohammad Mushfiqur Rahim", "displayName": "Mushfiqur Rahim"}}, "fielder": {"athlete": {}}, "minutes": 0, "retiredText": ""}}, {"id": "141010", "clock": "00:00", "date": "2018-01-19T12:00", "playType": {"id": "1", "description": "run"}, "team": {"id": "25", "name": "Bangladesh", "abbreviation": "BDESH", "displayName": "Bangladesh"}, "mediaId": 0, "period": 1, "periodText": "1st innings", "preText": "Dananjaya back for his last over\n\nFerdous: \"Bangladesh is passing its golden era with fantastic 5, they should prolong this as long as possible meanwhile nourish the young star like Miraz, saifuddin, musaddek and mustfiz to the lead the future. \"", "text": "looped up on middle and off, nudged through square leg", "postText": "", "shortText": "Dananjaya to Mushfiqur Rahim, 1 run", "homeScore": "247/3", "awayScore": "0", "scoreValue": 1, "sequence": 104101, "athletesInvolved": [{"id": "574178", "name": "Akila Dananjaya", "shortName": "Dananjaya", "displayName": "Akila Dananjaya"}, {"id": "56029", "name": "Mushfiqur Rahim", "shortName": "Mushfiqur", "displayName": "Mushfiqur Rahim"}], "speedKPH": "", "speedMPH": "", "bowler": {"athlete": {"id": "574178", "name": "Akila Dananjaya", "shortName": "Dananjaya", "fullName": "Mahamarakkala Kurukulasooriya Patabendige Akila Dananjaya Perera", "displayName": "Akila Dananjaya"}, "team": {"id": "8", "name": "Sri Lanka", "abbreviation": "SL", "displayName": "Sri Lanka"}, "maidens": 0, "balls": 55, "wickets": 1, "overs": 9.1, "conceded": 38}, "otherBowler": {"athlete": {"id": "784379", "name": "Wanindu Hasaranga", "shortName": "de Silva", "fullName": "Pinnaduwage Wanindu Hasaranga de Silva", "displayName": "Wanindu Hasaranga"}, "team": {"id": "8", "name": "Sri Lanka", "abbreviation": "SL", "displayName": "Sri Lanka"}, "maidens": 0, "balls": 30, "wickets": 0, "overs": 5.0, "conceded": 35}, "batsman": {"athlete": {"id": "56029", "name": "Mushfiqur Rahim", "shortName": "Mushfiqur", "fullName": "Mohammad Mushfiqur Rahim", "displayName": "Mushfiqur Rahim"}, "team": {"id": "25", "name": "Bangladesh", "abbreviation": "BDESH", "displayName": "Bangladesh"}, "totalRuns": 42, "faced": 36, "fours": 2, "runs": 247, "sixes": 1}, "otherBatsman": {"athlete": {"id": "56025", "name": "Mahmudullah", "shortName": "Mahmudullah", "fullName": "Mohammad Mahmudullah", "displayName": "Mahmudullah"}, "team": {"id": "25", "name": "Bangladesh", "abbreviation": "BDESH", "displayName": "Bangladesh"}, "totalRuns": 8, "faced": 9, "fours": 1, "runs": 0, "sixes": 0}, "innings": {"id": "202064", "runRate": 6.0, "remainingBalls": 53, "byes": 0, "number": 1, "balls": 247, "noBalls": 0, "wickets": 3, "legByes": 0, "ballLimit": 300, "target": 0, "session": 1, "day": 1, "fallOfWickets": 0, "remainingOvers": 0.0, "totalRuns": 1, "wides": 0, "runs": 247}, "over": {"ball": 1, "balls": 6, "complete": false, "limit": 50.0, "maiden": 0, "noBall": 0, "wide": 0, "byes": 0, "legByes": 0, "number": 42, "runs": 3, "wickets": 0, "overs": 41.1, "actual": 41.1, "unique": 41.01}, "dismissal": {"dismissal": false, "bowled": false, "type": "", "bowler": {"athlete": {"id": "574178", "name": "Akila Dananjaya", "shortName": "Dananjaya", "fullName": "Mahamarakkala Kurukulasooriya Patabendige Akila Dananjaya Perera", "displayName": "Akila Dananjaya"}}, "batsman": {"athlete": {"id": "56029", "name": "Mushfiqur Rahim", "shortName": "Mushfiqur", "fullName": "Mohammad Mushfiqur Rahim", "displayName": "Mushfiqur Rahim"}}, "fielder": {"athlete": {}}, "minutes": 0, "retiredText": ""}}, {"id": "141020", "clock": "00:00", "date": "2018-01-19T12:00", "playType": {"id": "1", "description": "run"}, "team": {"id": "25", "name": "Bangladesh", "abbreviation": "BDESH", "displayName": "Bangladesh"}, "mediaId": 0, "period": 1, "periodText": "1st innings", "preText": "", "text": "length ball, pitches outside leg and comes on around middle, waits and turns it away into midwicket", "postText": "", "shortText": "Dananjaya to Mahmudullah, 1 run", "homeScore": "248/3", "awayScore": "0", "scoreValue": 1, "sequence": 104102, "athletesInvolved": [{"id": "56025", "name": "Mahmudullah", "shortName": "Mahmudullah", "displayName": "Mahmudullah"}, {"id": "574178", "name": "Akila Dananjaya", "shortName": "Dananjaya", "displayName": "Akila Dananjaya"}], "speedKPH": "", "speedMPH": "", "bowler": {"athlete": {"id": "574178", "name": "Akila Dananjaya", "shortName": "Dananjaya", "fullName": "Mahamarakkala Kurukulasooriya Patabendige Akila Dananjaya Perera", "displayName": "Akila Dananjaya"}, "team": {"id": "8", "name": "Sri Lanka", "abbreviation": "SL", "displayName": "Sri Lanka"}, "maidens": 0, "balls": 56, "wickets": 1, "overs": 9.2, "conceded": 39}, "otherBowler": {"athlete": {"id": "784379", "name": "Wanindu Hasaranga", "shortName": "de Silva", "fullName": "Pinnaduwage Wanindu Hasaranga de Silva", "displayName": "Wanindu Hasaranga"}, "team": {"id": "8", "name": "Sri Lanka", "abbreviation": "SL", "displayName": "Sri Lanka"}, "maidens": 0, "balls": 30, "wickets": 0, "overs": 5.0, "conceded": 35}, "batsman": {"athlete": {"id": "56025", "name": "Mahmudullah", "shortName": "Mahmudullah", "fullName": "Mohammad Mahmudullah", "displayName": "Mahmudullah"}, "team": {"id": "25", "name": "Bangladesh", "abbreviation": "BDESH", "displayName": "Bangladesh"}, "totalRuns": 9, "faced": 10, "fours": 1, "runs": 248, "sixes": 0}, "otherBatsman": {"athlete": {"id": "56029", "name": "Mushfiqur Rahim", "shortName": "Mushfiqur", "fullName": "Mohammad Mushfiqur Rahim", "displayName": "Mushfiqur Rahim"}, "team": {"id": "25", "name": "Bangladesh", "abbreviation": "BDESH", "displayName": "Bangladesh"}, "totalRuns": 42, "faced": 36, "fours": 2, "runs": 0, "sixes": 1}, "innings": {"id": "202064", "runRate": 6.0, "remainingBalls": 52, "byes": 0, "number": 1, "balls": 248, "noBalls": 0, "wickets": 3, "legByes": 0, "ballLimit": 300, "target": 0, "session": 1, "day": 1, "fallOfWickets": 0, "remainingOvers": 0.0, "totalRuns": 1, "wides": 0, "runs": 248}, "over": {"ball": 2, "balls": 6, "complete": false, "limit": 50.0, "maiden": 0, "noBall": 0, "wide": 0, "byes": 0, "legByes": 0, "number": 42, "runs": 3, "wickets": 0, "overs": 41.2, "actual": 41.2, "unique": 41.02}, "dismissal": {"dismissal": false, "bowled": false, "type": "", "bowler": {"athlete": {"id": "574178", "name": "Akila Dananjaya", "shortName": "Dananjaya", "fullName": "Mahamarakkala Kurukulasooriya Patabendige Akila Dananjaya Perera", "displayName": "Akila Dananjaya"}}, "batsman": {"athlete": {"id": "56025", "name": "Mahmudullah", "shortName": "Mahmudullah", "fullName": "Mohammad Mahmudullah", "displayName": "Mahmudullah"}}, "fielder": {"athlete": {}}, "minutes": 0, "retiredText": ""}}, {"id": "141030", "clock": "00:00", "date": "2018-01-19T12:00", "playType": {"id": "1", "description": "run"}, "team": {"id": "25", "name": "Bangladesh", "abbreviation": "BDESH", "displayName": "Bangladesh"}, "mediaId": 0, "period": 1, "periodText": "1st innings", "preText": "", "text": "slightly shorter this time, waits for it and then pats it into the leg side", "postText": "", "shortText": "Dananjaya to Mushfiqur Rahim, 1 run", "homeScore": "249/3", "awayScore": "0", "scoreValue": 1, "sequence": 104103, "athletesInvolved": [{"id": "574178", "name": "Akila Dananjaya", "shortName": "Dananjaya", "displayName": "Akila Dananjaya"}, {"id": "56029", "name": "Mushfiqur Rahim", "shortName": "Mushfiqur", "displayName": "Mushfiqur Rahim"}], "speedKPH": "", "speedMPH": "", "bowler": {"athlete": {"id": "574178", "name": "Akila Dananjaya", "shortName": "Dananjaya", "fullName": "Mahamarakkala Kurukulasooriya Patabendige Akila Dananjaya Perera", "displayName": "Akila Dananjaya"}, "team": {"id": "8", "name": "Sri Lanka", "abbreviation": "SL", "displayName": "Sri Lanka"}, "maidens": 0, "balls": 57, "wickets": 1, "overs": 9.3, "conceded": 40}, "otherBowler": {"athlete": {"id": "784379", "name": "Wanindu Hasaranga", "shortName": "de Silva", "fullName": "Pinnaduwage Wanindu Hasaranga de Silva", "displayName": "Wanindu Hasaranga"}, "team": {"id": "8", "name": "Sri Lanka", "abbreviation": "SL", "displayName": "Sri Lanka"}, "maidens": 0, "balls": 30, "wickets": 0, "overs": 5.0, "conceded": 35}, "batsman": {"athlete": {"id": "56029", "name": "Mushfiqur Rahim", "shortName": "Mushfiqur", "fullName": "Mohammad Mushfiqur Rahim", "displayName": "Mushfiqur Rahim"}, "team": {"id": "25", "name": "Bangladesh", "abbreviation": "BDESH", "displayName": "Bangladesh"}, "totalRuns": 43, "faced": 37, "fours": 2, "runs": 249, "sixes": 1}, "otherBatsman": {"athlete": {"id": "56025", "name": "Mahmudullah", "shortName": "Mahmudullah", "fullName": "Mohammad Mahmudullah", "displayName": "Mahmudullah"}, "team": {"id": "25", "name": "Bangladesh", "abbreviation": "BDESH", "displayName": "Bangladesh"}, "totalRuns": 9, "faced": 10, "fours": 1, "runs": 0, "sixes": 0}, "innings": {"id": "202064", "runRate": 6.0, "remainingBalls": 51, "byes": 0, "number": 1, "balls": 249, "noBalls": 0, "wickets": 3, "legByes": 0, "ballLimit": 300, "target": 0, "session": 1, "day": 1, "fallOfWickets": 0, "remainingOvers": 0.0, "totalRuns": 1, "wides": 0, "runs": 249}, "over": {"ball": 3, "balls": 6, "complete": false, "limit": 50.0, "maiden": 0, "noBall": 0, "wide": 0, "byes": 0, "legByes": 0, "number": 42, "runs": 3, "wickets": 0, "overs": 41.3, "actual": 41.3, "unique": 41.03}, "dismissal": {"dismissal": false, "bowled": false, "type": "", "bowler": {"athlete": {"id": "574178", "name": "Akila Dananjaya", "shortName": "Dananjaya", "fullName": "Mahamarakkala Kurukulasooriya Patabendige Akila Dananjaya Perera", "displayName": "Akila Dananjaya"}}, "batsman": {"athlete": {"id": "56029", "name": "Mushfiqur Rahim", "shortName": "Mushfiqur", "fullName": "Mohammad Mushfiqur Rahim", "displayName": "Mushfiqur Rahim"}}, "fielder": {"athlete": {}}, "minutes": 0, "retiredText": ""}}, {"id": "141040", "clock": "00:00", "date": "2018-01-19T12:00", "playType": {"id": "2", "description": "no run"}, "team": {"id": "25", "name": "Bangladesh", "abbreviation": "BDESH", "displayName": "Bangladesh"}, "mediaId": 0, "period": 1, "periodText": "1st innings", "preText": "", "text": "loops it up on leg, comes forward early and gets hit on the pad as it bounces extra", "postText": "", "shortText": "Dananjaya to Mahmudullah, no run", "homeScore": "249/3", "awayScore": "0", "scoreValue": 0, "sequence": 104104, "athletesInvolved": [{"id": "56025", "name": "Mahmudullah", "shortName": "Mahmudullah", "displayName": "Mahmudullah"}, {"id": "574178", "name": "Akila Dananjaya", "shortName": "Dananjaya", "displayName": "Akila Dananjaya"}], "speedKPH": "", "speedMPH": "", "bowler": {"athlete": {"id": "574178", "name": "Akila Dananjaya", "shortName": "Dananjaya", "fullName": "Mahamarakkala Kurukulasooriya Patabendige Akila Dananjaya Perera", "displayName": "Akila Dananjaya"}, "team": {"id": "8", "name": "Sri Lanka", "abbreviation": "SL", "displayName": "Sri Lanka"}, "maidens": 0, "balls": 58, "wickets": 1, "overs": 9.4, "conceded": 40}, "otherBowler": {"athlete": {"id": "784379", "name": "Wanindu Hasaranga", "shortName": "de Silva", "fullName": "Pinnaduwage Wanindu Hasaranga de Silva", "displayName": "Wanindu Hasaranga"}, "team": {"id": "8", "name": "Sri Lanka", "abbreviation": "SL", "displayName": "Sri Lanka"}, "maidens": 0, "balls": 30, "wickets": 0, "overs": 5.0, "conceded": 35}, "batsman": {"athlete": {"id": "56025", "name": "Mahmudullah", "shortName": "Mahmudullah", "fullName": "Mohammad Mahmudullah", "displayName": "Mahmudullah"}, "team": {"id": "25", "name": "Bangladesh", "abbreviation": "BDESH", "displayName": "Bangladesh"}, "totalRuns": 9, "faced": 11, "fours": 1, "runs": 249, "sixes": 0}, "otherBatsman": {"athlete": {"id": "56029", "name": "Mushfiqur Rahim", "shortName": "Mushfiqur", "fullName": "Mohammad Mushfiqur Rahim", "displayName": "Mushfiqur Rahim"}, "team": {"id": "25", "name": "Bangladesh", "abbreviation": "BDESH", "displayName": "Bangladesh"}, "totalRuns": 43, "faced": 37, "fours": 2, "runs": 0, "sixes": 1}, "innings": {"id": "202064", "runRate": 5.97, "remainingBalls": 50, "byes": 0, "number": 1, "balls": 250, "noBalls": 0, "wickets": 3, "legByes": 0, "ballLimit": 300, "target": 0, "session": 1, "day": 1, "fallOfWickets": 0, "remainingOvers": 0.0, "totalRuns": 0, "wides": 0, "runs": 249}, "over": {"ball": 4, "balls": 6, "complete": false, "limit": 50.0, "maiden": 0, "noBall": 0, "wide": 0, "byes": 0, "legByes": 0, "number": 42, "runs": 3, "wickets": 0, "overs": 41.4, "actual": 41.4, "unique": 41.04}, "dismissal": {"dismissal": false, "bowled": false, "type": "", "bowler": {"athlete": {"id": "574178", "name": "Akila Dananjaya", "shortName": "Dananjaya", "fullName": "Mahamarakkala Kurukulasooriya Patabendige Akila Dananjaya Perera", "displayName": "Akila Dananjaya"}}, "batsman": {"athlete": {"id": "56025", "name": "Mahmudullah", "shortName": "Mahmudullah", "fullName": "Mohammad Mahmudullah", "displayName": "Mahmudullah"}}, "fielder": {"athlete": {}}, "minutes": 0, "retiredText": ""}}, {"id": "141050", "clock": "00:00", "date": "2018-01-19T12:00", "playType": {"id": "2", "description": "no run"}, "team": {"id": "25", "name": "Bangladesh", "abbreviation": "BDESH", "displayName": "Bangladesh"}, "mediaId": 0, "period": 1, "periodText": "1st innings", "preText": "", "text": "full on middle and leg, defended", "postText": "", "shortText": "Dananjaya to Mahmudullah, no run", "homeScore": "249/3", "awayScore": "0", "scoreValue": 0, "sequence": 104105, "athletesInvolved": [{"id": "56025", "name": "Mahmudullah", "shortName": "Mahmudullah", "displayName": "Mahmudullah"}, {"id": "574178", "name": "Akila Dananjaya", "shortName": "Dananjaya", "displayName": "Akila Dananjaya"}], "speedKPH": "", "speedMPH": "", "bowler": {"athlete": {"id": "574178", "name": "Akila Dananjaya", "shortName": "Dananjaya", "fullName": "Mahamarakkala Kurukulasooriya Patabendige Akila Dananjaya Perera", "displayName": "Akila Dananjaya"}, "team": {"id": "8", "name": "Sri Lanka", "abbreviation": "SL", "displayName": "Sri Lanka"}, "maidens": 0, "balls": 59, "wickets": 1, "overs": 9.5, "conceded": 40}, "otherBowler": {"athlete": {"id": "784379", "name": "Wanindu Hasaranga", "shortName": "de Silva", "fullName": "Pinnaduwage Wanindu Hasaranga de Silva", "displayName": "Wanindu Hasaranga"}, "team": {"id": "8", "name": "Sri Lanka", "abbreviation": "SL", "displayName": "Sri Lanka"}, "maidens": 0, "balls": 30, "wickets": 0, "overs": 5.0, "conceded": 35}, "batsman": {"athlete": {"id": "56025", "name": "Mahmudullah", "shortName": "Mahmudullah", "fullName": "Mohammad Mahmudullah", "displayName": "Mahmudullah"}, "team": {"id": "25", "name": "Bangladesh", "abbreviation": "BDESH", "displayName": "Bangladesh"}, "totalRuns": 9, "faced": 12, "fours": 1, "runs": 249, "sixes": 0}, "otherBatsman": {"athlete": {"id": "56029", "name": "Mushfiqur Rahim", "shortName": "Mushfiqur", "fullName": "Mohammad Mushfiqur Rahim", "displayName": "Mushfiqur Rahim"}, "team": {"id": "25", "name": "Bangladesh", "abbreviation": "BDESH", "displayName": "Bangladesh"}, "totalRuns": 43, "faced": 37, "fours": 2, "runs": 0, "sixes": 1}, "innings": {"id": "202064", "runRate": 5.95, "remainingBalls": 49, "byes": 0, "number": 1, "balls": 251, "noBalls": 0, "wickets": 3, "legByes": 0, "ballLimit": 300, "target": 0, "session": 1, "day": 1, "fallOfWickets": 0, "remainingOvers": 0.0, "totalRuns": 0, "wides": 0, "runs": 249}, "over": {"ball": 5, "balls": 6, "complete": false, "limit": 50.0, "maiden": 0, "noBall": 0, "wide": 0, "byes": 0, "legByes": 0, "number": 42, "runs": 3, "wickets": 0, "overs": 41.5, "actual": 41.5, "unique": 41.05}, "dismissal": {"dismissal": false, "bowled": false, "type": "", "bowler": {"athlete": {"id": "574178", "name": "Akila Dananjaya", "shortName": "Dananjaya", "fullName": "Mahamarakkala Kurukulasooriya Patabendige Akila Dananjaya Perera", "displayName": "Akila Dananjaya"}}, "batsman": {"athlete": {"id": "56025", "name": "Mahmudullah", "shortName": "Mahmudullah", "fullName": "Mohammad Mahmudullah", "displayName": "Mahmudullah"}}, "fielder": {"athlete": {}}, "minutes": 0, "retiredText": ""}}, {"id": "141060", "clock": "00:00", "date": "2018-01-19T12:00", "playType": {"id": "2", "description": "no run"}, "team": {"id": "25", "name": "Bangladesh", "abbreviation": "BDESH", "displayName": "Bangladesh"}, "mediaId": 0, "period": 1, "periodText": "1st innings", "preText": "", "text": "another shout for lbw. Gets past the attempted flick and hits the pad as it slides into him and tucks him up", "postText": "", "shortText": "Dananjaya to Mahmudullah, no run", "homeScore": "249/3", "awayScore": "0", "scoreValue": 0, "sequence": 104106, "athletesInvolved": [{"id": "56025", "name": "Mahmudullah", "shortName": "Mahmudullah", "displayName": "Mahmudullah"}, {"id": "574178", "name": "Akila Dananjaya", "shortName": "Dananjaya", "displayName": "Akila Dananjaya"}], "speedKPH": "", "speedMPH": "", "bowler": {"athlete": {"id": "574178", "name": "Akila Dananjaya", "shortName": "Dananjaya", "fullName": "Mahamarakkala Kurukulasooriya Patabendige Akila Dananjaya Perera", "displayName": "Akila Dananjaya"}, "team": {"id": "8", "name": "Sri Lanka", "abbreviation": "SL", "displayName": "Sri Lanka"}, "maidens": 0, "balls": 60, "wickets": 1, "overs": 10.0, "conceded": 40}, "otherBowler": {"athlete": {"id": "784379", "name": "Wanindu Hasaranga", "shortName": "de Silva", "fullName": "Pinnaduwage Wanindu Hasaranga de Silva", "displayName": "Wanindu Hasaranga"}, "team": {"id": "8", "name": "Sri Lanka", "abbreviation": "SL", "displayName": "Sri Lanka"}, "maidens": 0, "balls": 30, "wickets": 0, "overs": 5.0, "conceded": 35}, "batsman": {"athlete": {"id": "56025", "name": "Mahmudullah", "shortName": "Mahmudullah", "fullName": "Mohammad Mahmudullah", "displayName": "Mahmudullah"}, "team": {"id": "25", "name": "Bangladesh", "abbreviation": "BDESH", "displayName": "Bangladesh"}, "totalRuns": 9, "faced": 13, "fours": 1, "runs": 249, "sixes": 0}, "otherBatsman": {"athlete": {"id": "56029", "name": "Mushfiqur Rahim", "shortName": "Mushfiqur", "fullName": "Mohammad Mushfiqur Rahim", "displayName": "Mushfiqur Rahim"}, "team": {"id": "25", "name": "Bangladesh", "abbreviation": "BDESH", "displayName": "Bangladesh"}, "totalRuns": 43, "faced": 37, "fours": 2, "runs": 0, "sixes": 1}, "innings": {"id": "202064", "runRate": 5.92, "remainingBalls": 48, "byes": 0, "number": 1, "balls": 252, "noBalls": 0, "wickets": 3, "legByes": 0, "ballLimit": 300, "target": 0, "session": 1, "day": 1, "fallOfWickets": 0, "remainingOvers": 0.0, "totalRuns": 0, "wides": 0, "runs": 249}, "over": {"ball": 6, "balls": 6, "complete": true, "limit": 50.0, "maiden": 0, "noBall": 0, "wide": 0, "byes": 0, "legByes": 0, "number": 42, "runs": 3, "wickets": 0, "overs": 41.6, "actual": 41.6, "unique": 41.06}, "dismissal": {"dismissal": false, "bowled": false, "type": "", "bowler": {"athlete": {"id": "574178", "name": "Akila Dananjaya", "shortName": "Dananjaya", "fullName": "Mahamarakkala Kurukulasooriya Patabendige Akila Dananjaya Perera", "displayName": "Akila Dananjaya"}}, "batsman": {"athlete": {"id": "56025", "name": "Mahmudullah", "shortName": "Mahmudullah", "fullName": "Mohammad Mahmudullah", "displayName": "Mahmudullah"}}, "fielder": {"athlete": {}}, "minutes": 0, "retiredText": ""}}, {"id": "142010", "clock": "00:00", "date": "2018-01-19T12:00", "playType": {"id": "2", "description": "no run"}, "team": {"id": "25", "name": "Bangladesh", "abbreviation": "BDESH", "displayName": "Bangladesh"}, "mediaId": 0, "period": 1, "periodText": "1st innings", "preText": "", "text": "full outside off, backs away and switches around for a reverse sweep to backward point", "postText": "", "shortText": "de Silva to Mushfiqur Rahim, no run", "homeScore": "249/3", "awayScore": "0", "scoreValue": 0, "sequence": 104201, "athletesInvolved": [{"id": "784379", "name": "Wanindu Hasaranga", "shortName": "de Silva", "displayName": "Wanindu Hasaranga"}, {"id": "56029", "name": "Mushfiqur Rahim", "shortName": "Mushfiqur", "displayName": "Mushfiqur Rahim"}], "speedKPH": "", "speedMPH": "", "bowler": {"athlete": {"id": "784379", "name": "Wanindu Hasaranga", "shortName": "de Silva", "fullName": "Pinnaduwage Wanindu Hasaranga de Silva", "displayName": "Wanindu Hasaranga"}, "team": {"id": "8", "name": "Sri Lanka", "abbreviation": "SL", "displayName": "Sri Lanka"}, "maidens": 0, "balls": 31, "wickets": 0, "overs": 5.1, "conceded": 35}, "otherBowler": {"athlete": {"id": "574178", "name": "Akila Dananjaya", "shortName": "Dananjaya", "fullName": "Mahamarakkala Kurukulasooriya Patabendige Akila Dananjaya Perera", "displayName": "Akila Dananjaya"}, "team": {"id": "8", "name": "Sri Lanka", "abbreviation": "SL", "displayName": "Sri Lanka"}, "maidens": 0, "balls": 60, "wickets": 1, "overs": 10.0, "conceded": 40}, "batsman": {"athlete": {"id": "56029", "name": "Mushfiqur Rahim", "shortName": "Mushfiqur", "fullName": "Mohammad Mushfiqur Rahim", "displayName": "Mushfiqur Rahim"}, "team": {"id": "25", "name": "Bangladesh", "abbreviation": "BDESH", "displayName": "Bangladesh"}, "totalRuns": 43, "faced": 38, "fours": 2, "runs": 249, "sixes": 1}, "otherBatsman": {"athlete": {"id": "56025", "name": "Mahmudullah", "shortName": "Mahmudullah", "fullName": "Mohammad Mahmudullah", "displayName": "Mahmudullah"}, "team": {"id": "25", "name": "Bangladesh", "abbreviation": "BDESH", "displayName": "Bangladesh"}, "totalRuns": 9, "faced": 13, "fours": 1, "runs": 0, "sixes": 0}, "innings": {"id": "202064", "runRate": 5.9, "remainingBalls": 47, "byes": 0, "number": 1, "balls": 253, "noBalls": 0, "wickets": 3, "legByes": 0, "ballLimit": 300, "target": 0, "session": 1, "day": 1, "fallOfWickets": 0, "remainingOvers": 0.0, "totalRuns": 0, "wides": 0, "runs": 249}, "over": {"ball": 1, "balls": 6, "complete": false, "limit": 50.0, "maiden": 0, "noBall": 0, "wide": 0, "byes": 0, "legByes": 0, "number": 43, "runs": 4, "wickets": 0, "overs": 42.1, "actual": 42.1, "unique": 42.01}, "dismissal": {"dismissal": false, "bowled": false, "type": "", "bowler": {"athlete": {"id": "784379", "name": "Wanindu Hasaranga", "shortName": "de Silva", "fullName": "Pinnaduwage Wanindu Hasaranga de Silva", "displayName": "Wanindu Hasaranga"}}, "batsman": {"athlete": {"id": "56029", "name": "Mushfiqur Rahim", "shortName": "Mushfiqur", "fullName": "Mohammad Mushfiqur Rahim", "displayName": "Mushfiqur Rahim"}}, "fielder": {"athlete": {}}, "minutes": 0, "retiredText": ""}}, {"id": "142020", "clock": "00:00", "date": "2018-01-19T12:00", "playType": {"id": "1", "description": "run"}, "team": {"id": "25", "name": "Bangladesh", "abbreviation": "BDESH", "displayName": "Bangladesh"}, "mediaId": 0, "period": 1, "periodText": "1st innings", "preText": "", "text": "full on the stumps, driven down to long-on", "postText": "", "shortText": "de Silva to Mushfiqur Rahim, 1 run", "homeScore": "250/3", "awayScore": "0", "scoreValue": 1, "sequence": 104202, "athletesInvolved": [{"id": "784379", "name": "Wanindu Hasaranga", "shortName": "de Silva", "displayName": "Wanindu Hasaranga"}, {"id": "56029", "name": "Mushfiqur Rahim", "shortName": "Mushfiqur", "displayName": "Mushfiqur Rahim"}], "speedKPH": "", "speedMPH": "", "bowler": {"athlete": {"id": "784379", "name": "Wanindu Hasaranga", "shortName": "de Silva", "fullName": "Pinnaduwage Wanindu Hasaranga de Silva", "displayName": "Wanindu Hasaranga"}, "team": {"id": "8", "name": "Sri Lanka", "abbreviation": "SL", "displayName": "Sri Lanka"}, "maidens": 0, "balls": 32, "wickets": 0, "overs": 5.2, "conceded": 36}, "otherBowler": {"athlete": {"id": "574178", "name": "Akila Dananjaya", "shortName": "Dananjaya", "fullName": "Mahamarakkala Kurukulasooriya Patabendige Akila Dananjaya Perera", "displayName": "Akila Dananjaya"}, "team": {"id": "8", "name": "Sri Lanka", "abbreviation": "SL", "displayName": "Sri Lanka"}, "maidens": 0, "balls": 60, "wickets": 1, "overs": 10.0, "conceded": 40}, "batsman": {"athlete": {"id": "56029", "name": "Mushfiqur Rahim", "shortName": "Mushfiqur", "fullName": "Mohammad Mushfiqur Rahim", "displayName": "Mushfiqur Rahim"}, "team": {"id": "25", "name": "Bangladesh", "abbreviation": "BDESH", "displayName": "Bangladesh"}, "totalRuns": 44, "faced": 39, "fours": 2, "runs": 250, "sixes": 1}, "otherBatsman": {"athlete": {"id": "56025", "name": "Mahmudullah", "shortName": "Mahmudullah", "fullName": "Mohammad Mahmudullah", "displayName": "Mahmudullah"}, "team": {"id": "25", "name": "Bangladesh", "abbreviation": "BDESH", "displayName": "Bangladesh"}, "totalRuns": 9, "faced": 13, "fours": 1, "runs": 0, "sixes": 0}, "innings": {"id": "202064", "runRate": 5.9, "remainingBalls": 46, "byes": 0, "number": 1, "balls": 254, "noBalls": 0, "wickets": 3, "legByes": 0, "ballLimit": 300, "target": 0, "session": 1, "day": 1, "fallOfWickets": 0, "remainingOvers": 0.0, "totalRuns": 1, "wides": 0, "runs": 250}, "over": {"ball": 2, "balls": 6, "complete": false, "limit": 50.0, "maiden": 0, "noBall": 0, "wide": 0, "byes": 0, "legByes": 0, "number": 43, "runs": 4, "wickets": 0, "overs": 42.2, "actual": 42.2, "unique": 42.02}, "dismissal": {"dismissal": false, "bowled": false, "type": "", "bowler": {"athlete": {"id": "784379", "name": "Wanindu Hasaranga", "shortName": "de Silva", "fullName": "Pinnaduwage Wanindu Hasaranga de Silva", "displayName": "Wanindu Hasaranga"}}, "batsman": {"athlete": {"id": "56029", "name": "Mushfiqur Rahim", "shortName": "Mushfiqur", "fullName": "Mohammad Mushfiqur Rahim", "displayName": "Mushfiqur Rahim"}}, "fielder": {"athlete": {}}, "minutes": 0, "retiredText": ""}}, {"id": "142030", "clock": "00:00", "date": "2018-01-19T12:00", "playType": {"id": "2", "description": "no run"}, "team": {"id": "25", "name": "Bangladesh", "abbreviation": "BDESH", "displayName": "Bangladesh"}, "mediaId": 0, "period": 1, "periodText": "1st innings", "preText": "", "text": "chases a wide one for an extravagant drive but doesn't get close to it and inside-edges to the pad", "postText": "", "shortText": "de Silva to Mahmudullah, no run", "homeScore": "250/3", "awayScore": "0", "scoreValue": 0, "sequence": 104203, "athletesInvolved": [{"id": "784379", "name": "Wanindu Hasaranga", "shortName": "de Silva", "displayName": "Wanindu Hasaranga"}, {"id": "56025", "name": "Mahmudullah", "shortName": "Mahmudullah", "displayName": "Mahmudullah"}], "speedKPH": "", "speedMPH": "", "bowler": {"athlete": {"id": "784379", "name": "Wanindu Hasaranga", "shortName": "de Silva", "fullName": "Pinnaduwage Wanindu Hasaranga de Silva", "displayName": "Wanindu Hasaranga"}, "team": {"id": "8", "name": "Sri Lanka", "abbreviation": "SL", "displayName": "Sri Lanka"}, "maidens": 0, "balls": 33, "wickets": 0, "overs": 5.3, "conceded": 36}, "otherBowler": {"athlete": {"id": "574178", "name": "Akila Dananjaya", "shortName": "Dananjaya", "fullName": "Mahamarakkala Kurukulasooriya Patabendige Akila Dananjaya Perera", "displayName": "Akila Dananjaya"}, "team": {"id": "8", "name": "Sri Lanka", "abbreviation": "SL", "displayName": "Sri Lanka"}, "maidens": 0, "balls": 60, "wickets": 1, "overs": 10.0, "conceded": 40}, "batsman": {"athlete": {"id": "56025", "name": "Mahmudullah", "shortName": "Mahmudullah", "fullName": "Mohammad Mahmudullah", "displayName": "Mahmudullah"}, "team": {"id": "25", "name": "Bangladesh", "abbreviation": "BDESH", "displayName": "Bangladesh"}, "totalRuns": 9, "faced": 14, "fours": 1, "runs": 250, "sixes": 0}, "otherBatsman": {"athlete": {"id": "56029", "name": "Mushfiqur Rahim", "shortName": "Mushfiqur", "fullName": "Mohammad Mushfiqur Rahim", "displayName": "Mushfiqur Rahim"}, "team": {"id": "25", "name": "Bangladesh", "abbreviation": "BDESH", "displayName": "Bangladesh"}, "totalRuns": 44, "faced": 39, "fours": 2, "runs": 0, "sixes": 1}, "innings": {"id": "202064", "runRate": 5.88, "remainingBalls": 45, "byes": 0, "number": 1, "balls": 255, "noBalls": 0, "wickets": 3, "legByes": 0, "ballLimit": 300, "target": 0, "session": 1, "day": 1, "fallOfWickets": 0, "remainingOvers": 0.0, "totalRuns": 0, "wides": 0, "runs": 250}, "over": {"ball": 3, "balls": 6, "complete": false, "limit": 50.0, "maiden": 0, "noBall": 0, "wide": 0, "byes": 0, "legByes": 0, "number": 43, "runs": 4, "wickets": 0, "overs": 42.3, "actual": 42.3, "unique": 42.03}, "dismissal": {"dismissal": false, "bowled": false, "type": "", "bowler": {"athlete": {"id": "784379", "name": "Wanindu Hasaranga", "shortName": "de Silva", "fullName": "Pinnaduwage Wanindu Hasaranga de Silva", "displayName": "Wanindu Hasaranga"}}, "batsman": {"athlete": {"id": "56025", "name": "Mahmudullah", "shortName": "Mahmudullah", "fullName": "Mohammad Mahmudullah", "displayName": "Mahmudullah"}}, "fielder": {"athlete": {}}, "minutes": 0, "retiredText": ""}}, {"id": "142040", "clock": "00:00", "date": "2018-01-19T12:00", "playType": {"id": "1", "description": "run"}, "team": {"id": "25", "name": "Bangladesh", "abbreviation": "BDESH", "displayName": "Bangladesh"}, "mediaId": 0, "period": 1, "periodText": "1st innings", "preText": "", "text": "extremely full outside off, squeezed out through the gap at covers", "postText": "", "shortText": "de Silva to Mahmudullah, 1 run", "homeScore": "251/3", "awayScore": "0", "scoreValue": 1, "sequence": 104204, "athletesInvolved": [{"id": "784379", "name": "Wanindu Hasaranga", "shortName": "de Silva", "displayName": "Wanindu Hasaranga"}, {"id": "56025", "name": "Mahmudullah", "shortName": "Mahmudullah", "displayName": "Mahmudullah"}], "speedKPH": "", "speedMPH": "", "bowler": {"athlete": {"id": "784379", "name": "Wanindu Hasaranga", "shortName": "de Silva", "fullName": "Pinnaduwage Wanindu Hasaranga de Silva", "displayName": "Wanindu Hasaranga"}, "team": {"id": "8", "name": "Sri Lanka", "abbreviation": "SL", "displayName": "Sri Lanka"}, "maidens": 0, "balls": 34, "wickets": 0, "overs": 5.4, "conceded": 37}, "otherBowler": {"athlete": {"id": "574178", "name": "Akila Dananjaya", "shortName": "Dananjaya", "fullName": "Mahamarakkala Kurukulasooriya Patabendige Akila Dananjaya Perera", "displayName": "Akila Dananjaya"}, "team": {"id": "8", "name": "Sri Lanka", "abbreviation": "SL", "displayName": "Sri Lanka"}, "maidens": 0, "balls": 60, "wickets": 1, "overs": 10.0, "conceded": 40}, "batsman": {"athlete": {"id": "56025", "name": "Mahmudullah", "shortName": "Mahmudullah", "fullName": "Mohammad Mahmudullah", "displayName": "Mahmudullah"}, "team": {"id": "25", "name": "Bangladesh", "abbreviation": "BDESH", "displayName": "Bangladesh"}, "totalRuns": 10, "faced": 15, "fours": 1, "runs": 251, "sixes": 0}, "otherBatsman": {"athlete": {"id": "56029", "name": "Mushfiqur Rahim", "shortName": "Mushfiqur", "fullName": "Mohammad Mushfiqur Rahim", "displayName": "Mushfiqur Rahim"}, "team": {"id": "25", "name": "Bangladesh", "abbreviation": "BDESH", "displayName": "Bangladesh"}, "totalRuns": 44, "faced": 39, "fours": 2, "runs": 0, "sixes": 1}, "innings": {"id": "202064", "runRate": 5.88, "remainingBalls": 44, "byes": 0, "number": 1, "balls": 256, "noBalls": 0, "wickets": 3, "legByes": 0, "ballLimit": 300, "target": 0, "session": 1, "day": 1, "fallOfWickets": 0, "remainingOvers": 0.0, "totalRuns": 1, "wides": 0, "runs": 251}, "over": {"ball": 4, "balls": 6, "complete": false, "limit": 50.0, "maiden": 0, "noBall": 0, "wide": 0, "byes": 0, "legByes": 0, "number": 43, "runs": 4, "wickets": 0, "overs": 42.4, "actual": 42.4, "unique": 42.04}, "dismissal": {"dismissal": false, "bowled": false, "type": "", "bowler": {"athlete": {"id": "784379", "name": "Wanindu Hasaranga", "shortName": "de Silva", "fullName": "Pinnaduwage Wanindu Hasaranga de Silva", "displayName": "Wanindu Hasaranga"}}, "batsman": {"athlete": {"id": "56025", "name": "Mahmudullah", "shortName": "Mahmudullah", "fullName": "Mohammad Mahmudullah", "displayName": "Mahmudullah"}}, "fielder": {"athlete": {}}, "minutes": 0, "retiredText": ""}}, {"id": "142050", "clock": "00:00", "date": "2018-01-19T12:00", "playType": {"id": "1", "description": "run"}, "team": {"id": "25", "name": "Bangladesh", "abbreviation": "BDESH", "displayName": "Bangladesh"}, "mediaId": 0, "period": 1, "periodText": "1st innings", "preText": "", "text": "short of a length, straightening around middle from a leg-stump line, flicked against the turn to deep midwicket", "postText": "", "shortText": "de Silva to Mushfiqur Rahim, 1 run", "homeScore": "252/3", "awayScore": "0", "scoreValue": 1, "sequence": 104205, "athletesInvolved": [{"id": "784379", "name": "Wanindu Hasaranga", "shortName": "de Silva", "displayName": "Wanindu Hasaranga"}, {"id": "56029", "name": "Mushfiqur Rahim", "shortName": "Mushfiqur", "displayName": "Mushfiqur Rahim"}], "speedKPH": "", "speedMPH": "", "bowler": {"athlete": {"id": "784379", "name": "Wanindu Hasaranga", "shortName": "de Silva", "fullName": "Pinnaduwage Wanindu Hasaranga de Silva", "displayName": "Wanindu Hasaranga"}, "team": {"id": "8", "name": "Sri Lanka", "abbreviation": "SL", "displayName": "Sri Lanka"}, "maidens": 0, "balls": 35, "wickets": 0, "overs": 5.5, "conceded": 38}, "otherBowler": {"athlete": {"id": "574178", "name": "Akila Dananjaya", "shortName": "Dananjaya", "fullName": "Mahamarakkala Kurukulasooriya Patabendige Akila Dananjaya Perera", "displayName": "Akila Dananjaya"}, "team": {"id": "8", "name": "Sri Lanka", "abbreviation": "SL", "displayName": "Sri Lanka"}, "maidens": 0, "balls": 60, "wickets": 1, "overs": 10.0, "conceded": 40}, "batsman": {"athlete": {"id": "56029", "name": "Mushfiqur Rahim", "shortName": "Mushfiqur", "fullName": "Mohammad Mushfiqur Rahim", "displayName": "Mushfiqur Rahim"}, "team": {"id": "25", "name": "Bangladesh", "abbreviation": "BDESH", "displayName": "Bangladesh"}, "totalRuns": 45, "faced": 40, "fours": 2, "runs": 252, "sixes": 1}, "otherBatsman": {"athlete": {"id": "56025", "name": "Mahmudullah", "shortName": "Mahmudullah", "fullName": "Mohammad Mahmudullah", "displayName": "Mahmudullah"}, "team": {"id": "25", "name": "Bangladesh", "abbreviation": "BDESH", "displayName": "Bangladesh"}, "totalRuns": 10, "faced": 15, "fours": 1, "runs": 0, "sixes": 0}, "innings": {"id": "202064", "runRate": 5.88, "remainingBalls": 43, "byes": 0, "number": 1, "balls": 257, "noBalls": 0, "wickets": 3, "legByes": 0, "ballLimit": 300, "target": 0, "session": 1, "day": 1, "fallOfWickets": 0, "remainingOvers": 0.0, "totalRuns": 1, "wides": 0, "runs": 252}, "over": {"ball": 5, "balls": 6, "complete": false, "limit": 50.0, "maiden": 0, "noBall": 0, "wide": 0, "byes": 0, "legByes": 0, "number": 43, "runs": 4, "wickets": 0, "overs": 42.5, "actual": 42.5, "unique": 42.05}, "dismissal": {"dismissal": false, "bowled": false, "type": "", "bowler": {"athlete": {"id": "784379", "name": "Wanindu Hasaranga", "shortName": "de Silva", "fullName": "Pinnaduwage Wanindu Hasaranga de Silva", "displayName": "Wanindu Hasaranga"}}, "batsman": {"athlete": {"id": "56029", "name": "Mushfiqur Rahim", "shortName": "Mushfiqur", "fullName": "Mohammad Mushfiqur Rahim", "displayName": "Mushfiqur Rahim"}}, "fielder": {"athlete": {}}, "minutes": 0, "retiredText": ""}}, {"id": "142060", "clock": "00:00", "date": "2018-01-19T12:00", "playType": {"id": "1", "description": "run"}, "team": {"id": "25", "name": "Bangladesh", "abbreviation": "BDESH", "displayName": "Bangladesh"}, "mediaId": 0, "period": 1, "periodText": "1st innings", "preText": "", "text": "stays in the crease and stabs a length ball through the cover and point area", "postText": "", "shortText": "de Silva to Mahmudullah, 1 run", "homeScore": "253/3", "awayScore": "0", "scoreValue": 1, "sequence": 104206, "athletesInvolved": [{"id": "784379", "name": "Wanindu Hasaranga", "shortName": "de Silva", "displayName": "Wanindu Hasaranga"}, {"id": "56025", "name": "Mahmudullah", "shortName": "Mahmudullah", "displayName": "Mahmudullah"}], "speedKPH": "", "speedMPH": "", "bowler": {"athlete": {"id": "784379", "name": "Wanindu Hasaranga", "shortName": "de Silva", "fullName": "Pinnaduwage Wanindu Hasaranga de Silva", "displayName": "Wanindu Hasaranga"}, "team": {"id": "8", "name": "Sri Lanka", "abbreviation": "SL", "displayName": "Sri Lanka"}, "maidens": 0, "balls": 36, "wickets": 0, "overs": 6.0, "conceded": 39}, "otherBowler": {"athlete": {"id": "574178", "name": "Akila Dananjaya", "shortName": "Dananjaya", "fullName": "Mahamarakkala Kurukulasooriya Patabendige Akila Dananjaya Perera", "displayName": "Akila Dananjaya"}, "team": {"id": "8", "name": "Sri Lanka", "abbreviation": "SL", "displayName": "Sri Lanka"}, "maidens": 0, "balls": 60, "wickets": 1, "overs": 10.0, "conceded": 40}, "batsman": {"athlete": {"id": "56025", "name": "Mahmudullah", "shortName": "Mahmudullah", "fullName": "Mohammad Mahmudullah", "displayName": "Mahmudullah"}, "team": {"id": "25", "name": "Bangladesh", "abbreviation": "BDESH", "displayName": "Bangladesh"}, "totalRuns": 11, "faced": 16, "fours": 1, "runs": 253, "sixes": 0}, "otherBatsman": {"athlete": {"id": "56029", "name": "Mushfiqur Rahim", "shortName": "Mushfiqur", "fullName": "Mohammad Mushfiqur Rahim", "displayName": "Mushfiqur Rahim"}, "team": {"id": "25", "name": "Bangladesh", "abbreviation": "BDESH", "displayName": "Bangladesh"}, "totalRuns": 45, "faced": 40, "fours": 2, "runs": 0, "sixes": 1}, "innings": {"id": "202064", "runRate": 5.88, "remainingBalls": 42, "byes": 0, "number": 1, "balls": 258, "noBalls": 0, "wickets": 3, "legByes": 0, "ballLimit": 300, "target": 0, "session": 1, "day": 1, "fallOfWickets": 0, "remainingOvers": 0.0, "totalRuns": 1, "wides": 0, "runs": 253}, "over": {"ball": 6, "balls": 6, "complete": true, "limit": 50.0, "maiden": 0, "noBall": 0, "wide": 0, "byes": 0, "legByes": 0, "number": 43, "runs": 4, "wickets": 0, "overs": 42.6, "actual": 42.6, "unique": 42.06}, "dismissal": {"dismissal": false, "bowled": false, "type": "", "bowler": {"athlete": {"id": "784379", "name": "Wanindu Hasaranga", "shortName": "de Silva", "fullName": "Pinnaduwage Wanindu Hasaranga de Silva", "displayName": "Wanindu Hasaranga"}}, "batsman": {"athlete": {"id": "56025", "name": "Mahmudullah", "shortName": "Mahmudullah", "fullName": "Mohammad Mahmudullah", "displayName": "Mahmudullah"}}, "fielder": {"athlete": {}}, "minutes": 0, "retiredText": ""}}, {"id": "143010", "clock": "00:00", "date": "2018-01-19T12:00", "playType": {"id": "2", "description": "no run"}, "team": {"id": "25", "name": "Bangladesh", "abbreviation": "BDESH", "displayName": "Bangladesh"}, "mediaId": 0, "period": 1, "periodText": "1st innings", "preText": "Pradeep", "text": "short of a length, straying on the pads, tucked to square leg", "postText": "", "shortText": "Pradeep to Mahmudullah, no run", "homeScore": "253/3", "awayScore": "0", "scoreValue": 0, "sequence": 104301, "athletesInvolved": [{"id": "324358", "name": "Nuwan Pradeep", "shortName": "Pradeep", "displayName": "Nuwan Pradeep"}, {"id": "56025", "name": "Mahmudullah", "shortName": "Mahmudullah", "displayName": "Mahmudullah"}], "speedKPH": "", "speedMPH": "", "bowler": {"athlete": {"id": "324358", "name": "Nuwan Pradeep", "shortName": "Pradeep", "fullName": "Aththachchi Nuwan Pradeep Roshan Fernando", "displayName": "Nuwan Pradeep"}, "team": {"id": "8", "name": "Sri Lanka", "abbreviation": "SL", "displayName": "Sri Lanka"}, "maidens": 0, "balls": 43, "wickets": 0, "overs": 7.1, "conceded": 40}, "otherBowler": {"athlete": {"id": "784379", "name": "Wanindu Hasaranga", "shortName": "de Silva", "fullName": "Pinnaduwage Wanindu Hasaranga de Silva", "displayName": "Wanindu Hasaranga"}, "team": {"id": "8", "name": "Sri Lanka", "abbreviation": "SL", "displayName": "Sri Lanka"}, "maidens": 0, "balls": 36, "wickets": 0, "overs": 6.0, "conceded": 39}, "batsman": {"athlete": {"id": "56025", "name": "Mahmudullah", "shortName": "Mahmudullah", "fullName": "Mohammad Mahmudullah", "displayName": "Mahmudullah"}, "team": {"id": "25", "name": "Bangladesh", "abbreviation": "BDESH", "displayName": "Bangladesh"}, "totalRuns": 11, "faced": 17, "fours": 1, "runs": 253, "sixes": 0}, "otherBatsman": {"athlete": {"id": "56029", "name": "Mushfiqur Rahim", "shortName": "Mushfiqur", "fullName": "Mohammad Mushfiqur Rahim", "displayName": "Mushfiqur Rahim"}, "team": {"id": "25", "name": "Bangladesh", "abbreviation": "BDESH", "displayName": "Bangladesh"}, "totalRuns": 45, "faced": 40, "fours": 2, "runs": 0, "sixes": 1}, "innings": {"id": "202064", "runRate": 5.86, "remainingBalls": 41, "byes": 0, "number": 1, "balls": 259, "noBalls": 0, "wickets": 3, "legByes": 0, "ballLimit": 300, "target": 0, "session": 1, "day": 1, "fallOfWickets": 0, "remainingOvers": 0.0, "totalRuns": 0, "wides": 0, "runs": 253}, "over": {"ball": 1, "balls": 6, "complete": false, "limit": 50.0, "maiden": 0, "noBall": 0, "wide": 0, "byes": 0, "legByes": 0, "number": 44, "runs": 12, "wickets": 0, "overs": 43.1, "actual": 43.1, "unique": 43.01}, "dismissal": {"dismissal": false, "bowled": false, "type": "", "bowler": {"athlete": {"id": "324358", "name": "Nuwan Pradeep", "shortName": "Pradeep", "fullName": "Aththachchi Nuwan Pradeep Roshan Fernando", "displayName": "Nuwan Pradeep"}}, "batsman": {"athlete": {"id": "56025", "name": "Mahmudullah", "shortName": "Mahmudullah", "fullName": "Mohammad Mahmudullah", "displayName": "Mahmudullah"}}, "fielder": {"athlete": {}}, "minutes": 0, "retiredText": ""}}, {"id": "143020", "clock": "00:00", "date": "2018-01-19T12:00", "playType": {"id": "3", "description": "four"}, "team": {"id": "25", "name": "Bangladesh", "abbreviation": "BDESH", "displayName": "Bangladesh"}, "mediaId": 0, "period": 1, "periodText": "1st innings", "preText": "", "text": "short, not much width but he makes some by advancing down the ground, gets on top and slaps it through extra cover", "postText": "", "shortText": "Pradeep to Mahmudullah, FOUR runs", "homeScore": "257/3", "awayScore": "0", "scoreValue": 4, "sequence": 104302, "athletesInvolved": [{"id": "324358", "name": "Nuwan Pradeep", "shortName": "Pradeep", "displayName": "Nuwan Pradeep"}, {"id": "56025", "name": "Mahmudullah", "shortName": "Mahmudullah", "displayName": "Mahmudullah"}], "speedKPH": "", "speedMPH": "", "bowler": {"athlete": {"id": "324358", "name": "Nuwan Pradeep", "shortName": "Pradeep", "fullName": "Aththachchi Nuwan Pradeep Roshan Fernando", "displayName": "Nuwan Pradeep"}, "team": {"id": "8", "name": "Sri Lanka", "abbreviation": "SL", "displayName": "Sri Lanka"}, "maidens": 0, "balls": 44, "wickets": 0, "overs": 7.2, "conceded": 44}, "otherBowler": {"athlete": {"id": "784379", "name": "Wanindu Hasaranga", "shortName": "de Silva", "fullName": "Pinnaduwage Wanindu Hasaranga de Silva", "displayName": "Wanindu Hasaranga"}, "team": {"id": "8", "name": "Sri Lanka", "abbreviation": "SL", "displayName": "Sri Lanka"}, "maidens": 0, "balls": 36, "wickets": 0, "overs": 6.0, "conceded": 39}, "batsman": {"athlete": {"id": "56025", "name": "Mahmudullah", "shortName": "Mahmudullah", "fullName": "Mohammad Mahmudullah", "displayName": "Mahmudullah"}, "team": {"id": "25", "name": "Bangladesh", "abbreviation": "BDESH", "displayName": "Bangladesh"}, "totalRuns": 15, "faced": 18, "fours": 2, "runs": 257, "sixes": 0}, "otherBatsman": {"athlete": {"id": "56029", "name": "Mushfiqur Rahim", "shortName": "Mushfiqur", "fullName": "Mohammad Mushfiqur Rahim", "displayName": "Mushfiqur Rahim"}, "team": {"id": "25", "name": "Bangladesh", "abbreviation": "BDESH", "displayName": "Bangladesh"}, "totalRuns": 45, "faced": 40, "fours": 2, "runs": 0, "sixes": 1}, "innings": {"id": "202064", "runRate": 5.93, "remainingBalls": 40, "byes": 0, "number": 1, "balls": 260, "noBalls": 0, "wickets": 3, "legByes": 0, "ballLimit": 300, "target": 0, "session": 1, "day": 1, "fallOfWickets": 0, "remainingOvers": 0.0, "totalRuns": 4, "wides": 0, "runs": 257}, "over": {"ball": 2, "balls": 6, "complete": false, "limit": 50.0, "maiden": 0, "noBall": 0, "wide": 0, "byes": 0, "legByes": 0, "number": 44, "runs": 12, "wickets": 0, "overs": 43.2, "actual": 43.2, "unique": 43.02}, "dismissal": {"dismissal": false, "bowled": false, "type": "", "bowler": {"athlete": {"id": "324358", "name": "Nuwan Pradeep", "shortName": "Pradeep", "fullName": "Aththachchi Nuwan Pradeep Roshan Fernando", "displayName": "Nuwan Pradeep"}}, "batsman": {"athlete": {"id": "56025", "name": "Mahmudullah", "shortName": "Mahmudullah", "fullName": "Mohammad Mahmudullah", "displayName": "Mahmudullah"}}, "fielder": {"athlete": {}}, "minutes": 0, "retiredText": ""}}, {"id": "143030", "clock": "00:00", "date": "2018-01-19T12:00", "playType": {"id": "1", "description": "run"}, "team": {"id": "25", "name": "Bangladesh", "abbreviation": "BDESH", "displayName": "Bangladesh"}, "mediaId": 0, "period": 1, "periodText": "1st innings", "preText": "", "text": "slower length ball outside off, waits and opens the face to third man", "postText": "", "shortText": "Pradeep to Mahmudullah, 1 run", "homeScore": "258/3", "awayScore": "0", "scoreValue": 1, "sequence": 104303, "athletesInvolved": [{"id": "324358", "name": "Nuwan Pradeep", "shortName": "Pradeep", "displayName": "Nuwan Pradeep"}, {"id": "56025", "name": "Mahmudullah", "shortName": "Mahmudullah", "displayName": "Mahmudullah"}], "speedKPH": "", "speedMPH": "", "bowler": {"athlete": {"id": "324358", "name": "Nuwan Pradeep", "shortName": "Pradeep", "fullName": "Aththachchi Nuwan Pradeep Roshan Fernando", "displayName": "Nuwan Pradeep"}, "team": {"id": "8", "name": "Sri Lanka", "abbreviation": "SL", "displayName": "Sri Lanka"}, "maidens": 0, "balls": 45, "wickets": 0, "overs": 7.3, "conceded": 45}, "otherBowler": {"athlete": {"id": "784379", "name": "Wanindu Hasaranga", "shortName": "de Silva", "fullName": "Pinnaduwage Wanindu Hasaranga de Silva", "displayName": "Wanindu Hasaranga"}, "team": {"id": "8", "name": "Sri Lanka", "abbreviation": "SL", "displayName": "Sri Lanka"}, "maidens": 0, "balls": 36, "wickets": 0, "overs": 6.0, "conceded": 39}, "batsman": {"athlete": {"id": "56025", "name": "Mahmudullah", "shortName": "Mahmudullah", "fullName": "Mohammad Mahmudullah", "displayName": "Mahmudullah"}, "team": {"id": "25", "name": "Bangladesh", "abbreviation": "BDESH", "displayName": "Bangladesh"}, "totalRuns": 16, "faced": 19, "fours": 2, "runs": 258, "sixes": 0}, "otherBatsman": {"athlete": {"id": "56029", "name": "Mushfiqur Rahim", "shortName": "Mushfiqur", "fullName": "Mohammad Mushfiqur Rahim", "displayName": "Mushfiqur Rahim"}, "team": {"id": "25", "name": "Bangladesh", "abbreviation": "BDESH", "displayName": "Bangladesh"}, "totalRuns": 45, "faced": 40, "fours": 2, "runs": 0, "sixes": 1}, "innings": {"id": "202064", "runRate": 5.93, "remainingBalls": 39, "byes": 0, "number": 1, "balls": 261, "noBalls": 0, "wickets": 3, "legByes": 0, "ballLimit": 300, "target": 0, "session": 1, "day": 1, "fallOfWickets": 0, "remainingOvers": 0.0, "totalRuns": 1, "wides": 0, "runs": 258}, "over": {"ball": 3, "balls": 6, "complete": false, "limit": 50.0, "maiden": 0, "noBall": 0, "wide": 0, "byes": 0, "legByes": 0, "number": 44, "runs": 12, "wickets": 0, "overs": 43.3, "actual": 43.3, "unique": 43.03}, "dismissal": {"dismissal": false, "bowled": false, "type": "", "bowler": {"athlete": {"id": "324358", "name": "Nuwan Pradeep", "shortName": "Pradeep", "fullName": "Aththachchi Nuwan Pradeep Roshan Fernando", "displayName": "Nuwan Pradeep"}}, "batsman": {"athlete": {"id": "56025", "name": "Mahmudullah", "shortName": "Mahmudullah", "fullName": "Mohammad Mahmudullah", "displayName": "Mahmudullah"}}, "fielder": {"athlete": {}}, "minutes": 0, "retiredText": ""}}, {"id": "143040", "clock": "00:00", "date": "2018-01-19T12:00", "playType": {"id": "3", "description": "four"}, "team": {"id": "25", "name": "Bangladesh", "abbreviation": "BDESH", "displayName": "Bangladesh"}, "mediaId": 0, "period": 1, "periodText": "1st innings", "preText": "", "text": "<b>just over the keeper</b>. Pre-medidates a shuffle and the bowler drags the pace back but he gets down and scoops it just over the outstretched left hand of Dickwella", "postText": "", "shortText": "Pradeep to Mushfiqur Rahim, FOUR runs", "homeScore": "262/3", "awayScore": "0", "scoreValue": 4, "sequence": 104304, "athletesInvolved": [{"id": "324358", "name": "Nuwan Pradeep", "shortName": "Pradeep", "displayName": "Nuwan Pradeep"}, {"id": "56029", "name": "Mushfiqur Rahim", "shortName": "Mushfiqur", "displayName": "Mushfiqur Rahim"}], "speedKPH": "", "speedMPH": "", "bowler": {"athlete": {"id": "324358", "name": "Nuwan Pradeep", "shortName": "Pradeep", "fullName": "Aththachchi Nuwan Pradeep Roshan Fernando", "displayName": "Nuwan Pradeep"}, "team": {"id": "8", "name": "Sri Lanka", "abbreviation": "SL", "displayName": "Sri Lanka"}, "maidens": 0, "balls": 46, "wickets": 0, "overs": 7.4, "conceded": 49}, "otherBowler": {"athlete": {"id": "784379", "name": "Wanindu Hasaranga", "shortName": "de Silva", "fullName": "Pinnaduwage Wanindu Hasaranga de Silva", "displayName": "Wanindu Hasaranga"}, "team": {"id": "8", "name": "Sri Lanka", "abbreviation": "SL", "displayName": "Sri Lanka"}, "maidens": 0, "balls": 36, "wickets": 0, "overs": 6.0, "conceded": 39}, "batsman": {"athlete": {"id": "56029", "name": "Mushfiqur Rahim", "shortName": "Mushfiqur", "fullName": "Mohammad Mushfiqur Rahim", "displayName": "Mushfiqur Rahim"}, "team": {"id": "25", "name": "Bangladesh", "abbreviation": "BDESH", "displayName": "Bangladesh"}, "totalRuns": 49, "faced": 41, "fours": 3, "runs": 262, "sixes": 1}, "otherBatsman": {"athlete": {"id": "56025", "name": "Mahmudullah", "shortName": "Mahmudullah", "fullName": "Mohammad Mahmudullah", "displayName": "Mahmudullah"}, "team": {"id": "25", "name": "Bangladesh", "abbreviation": "BDESH", "displayName": "Bangladesh"}, "totalRuns": 16, "faced": 19, "fours": 2, "runs": 0, "sixes": 0}, "innings": {"id": "202064", "runRate": 6.0, "remainingBalls": 38, "byes": 0, "number": 1, "balls": 262, "noBalls": 0, "wickets": 3, "legByes": 0, "ballLimit": 300, "target": 0, "session": 1, "day": 1, "fallOfWickets": 0, "remainingOvers": 0.0, "totalRuns": 4, "wides": 0, "runs": 262}, "over": {"ball": 4, "balls": 6, "complete": false, "limit": 50.0, "maiden": 0, "noBall": 0, "wide": 0, "byes": 0, "legByes": 0, "number": 44, "runs": 12, "wickets": 0, "overs": 43.4, "actual": 43.4, "unique": 43.04}, "dismissal": {"dismissal": false, "bowled": false, "type": "", "bowler": {"athlete": {"id": "324358", "name": "Nuwan Pradeep", "shortName": "Pradeep", "fullName": "Aththachchi Nuwan Pradeep Roshan Fernando", "displayName": "Nuwan Pradeep"}}, "batsman": {"athlete": {"id": "56029", "name": "Mushfiqur Rahim", "shortName": "Mushfiqur", "fullName": "Mohammad Mushfiqur Rahim", "displayName": "Mushfiqur Rahim"}}, "fielder": {"athlete": {}}, "minutes": 0, "retiredText": ""}}, {"id": "143050", "clock": "00:00", "date": "2018-01-19T12:00", "playType": {"id": "1", "description": "run"}, "team": {"id": "25", "name": "Bangladesh", "abbreviation": "BDESH", "displayName": "Bangladesh"}, "mediaId": 0, "period": 1, "periodText": "1st innings", "preText": "", "text": "short ball, swivels around with a quick pull to deep backward square leg. Picks the gap to come back for a second. <b>And that's fifty for Rahim</b>. Valuable knock. He needs to stay till the end", "postText": "", "shortText": "Pradeep to Mushfiqur Rahim, 2 runs", "homeScore": "264/3", "awayScore": "0", "scoreValue": 2, "sequence": 104305, "athletesInvolved": [{"id": "324358", "name": "Nuwan Pradeep", "shortName": "Pradeep", "displayName": "Nuwan Pradeep"}, {"id": "56029", "name": "Mushfiqur Rahim", "shortName": "Mushfiqur", "displayName": "Mushfiqur Rahim"}], "speedKPH": "", "speedMPH": "", "bowler": {"athlete": {"id": "324358", "name": "Nuwan Pradeep", "shortName": "Pradeep", "fullName": "Aththachchi Nuwan Pradeep Roshan Fernando", "displayName": "Nuwan Pradeep"}, "team": {"id": "8", "name": "Sri Lanka", "abbreviation": "SL", "displayName": "Sri Lanka"}, "maidens": 0, "balls": 47, "wickets": 0, "overs": 7.5, "conceded": 51}, "otherBowler": {"athlete": {"id": "784379", "name": "Wanindu Hasaranga", "shortName": "de Silva", "fullName": "Pinnaduwage Wanindu Hasaranga de Silva", "displayName": "Wanindu Hasaranga"}, "team": {"id": "8", "name": "Sri Lanka", "abbreviation": "SL", "displayName": "Sri Lanka"}, "maidens": 0, "balls": 36, "wickets": 0, "overs": 6.0, "conceded": 39}, "batsman": {"athlete": {"id": "56029", "name": "Mushfiqur Rahim", "shortName": "Mushfiqur", "fullName": "Mohammad Mushfiqur Rahim", "displayName": "Mushfiqur Rahim"}, "team": {"id": "25", "name": "Bangladesh", "abbreviation": "BDESH", "displayName": "Bangladesh"}, "totalRuns": 51, "faced": 42, "fours": 3, "runs": 264, "sixes": 1}, "otherBatsman": {"athlete": {"id": "56025", "name": "Mahmudullah", "shortName": "Mahmudullah", "fullName": "Mohammad Mahmudullah", "displayName": "Mahmudullah"}, "team": {"id": "25", "name": "Bangladesh", "abbreviation": "BDESH", "displayName": "Bangladesh"}, "totalRuns": 16, "faced": 19, "fours": 2, "runs": 0, "sixes": 0}, "innings": {"id": "202064", "runRate": 6.02, "remainingBalls": 37, "byes": 0, "number": 1, "balls": 263, "noBalls": 0, "wickets": 3, "legByes": 0, "ballLimit": 300, "target": 0, "session": 1, "day": 1, "fallOfWickets": 0, "remainingOvers": 0.0, "totalRuns": 2, "wides": 0, "runs": 264}, "over": {"ball": 5, "balls": 6, "complete": false, "limit": 50.0, "maiden": 0, "noBall": 0, "wide": 0, "byes": 0, "legByes": 0, "number": 44, "runs": 12, "wickets": 0, "overs": 43.5, "actual": 43.5, "unique": 43.05}, "dismissal": {"dismissal": false, "bowled": false, "type": "", "bowler": {"athlete": {"id": "324358", "name": "Nuwan Pradeep", "shortName": "Pradeep", "fullName": "Aththachchi Nuwan Pradeep Roshan Fernando", "displayName": "Nuwan Pradeep"}}, "batsman": {"athlete": {"id": "56029", "name": "Mushfiqur Rahim", "shortName": "Mushfiqur", "fullName": "Mohammad Mushfiqur Rahim", "displayName": "Mushfiqur Rahim"}}, "fielder": {"athlete": {}}, "minutes": 0, "retiredText": ""}}, {"id": "143060", "clock": "00:00", "date": "2018-01-19T12:00", "playType": {"id": "1", "description": "run"}, "team": {"id": "25", "name": "Bangladesh", "abbreviation": "BDESH", "displayName": "Bangladesh"}, "mediaId": 0, "period": 1, "periodText": "1st innings", "preText": "", "text": "short of a length outside off, no pace again, waits before steering it down to third man", "postText": "", "shortText": "Pradeep to Mushfiqur Rahim, 1 run", "homeScore": "265/3", "awayScore": "0", "scoreValue": 1, "sequence": 104306, "athletesInvolved": [{"id": "324358", "name": "Nuwan Pradeep", "shortName": "Pradeep", "displayName": "Nuwan Pradeep"}, {"id": "56029", "name": "Mushfiqur Rahim", "shortName": "Mushfiqur", "displayName": "Mushfiqur Rahim"}], "speedKPH": "", "speedMPH": "", "bowler": {"athlete": {"id": "324358", "name": "Nuwan Pradeep", "shortName": "Pradeep", "fullName": "Aththachchi Nuwan Pradeep Roshan Fernando", "displayName": "Nuwan Pradeep"}, "team": {"id": "8", "name": "Sri Lanka", "abbreviation": "SL", "displayName": "Sri Lanka"}, "maidens": 0, "balls": 48, "wickets": 0, "overs": 8.0, "conceded": 52}, "otherBowler": {"athlete": {"id": "784379", "name": "Wanindu Hasaranga", "shortName": "de Silva", "fullName": "Pinnaduwage Wanindu Hasaranga de Silva", "displayName": "Wanindu Hasaranga"}, "team": {"id": "8", "name": "Sri Lanka", "abbreviation": "SL", "displayName": "Sri Lanka"}, "maidens": 0, "balls": 36, "wickets": 0, "overs": 6.0, "conceded": 39}, "batsman": {"athlete": {"id": "56029", "name": "Mushfiqur Rahim", "shortName": "Mushfiqur", "fullName": "Mohammad Mushfiqur Rahim", "displayName": "Mushfiqur Rahim"}, "team": {"id": "25", "name": "Bangladesh", "abbreviation": "BDESH", "displayName": "Bangladesh"}, "totalRuns": 52, "faced": 43, "fours": 3, "runs": 265, "sixes": 1}, "otherBatsman": {"athlete": {"id": "56025", "name": "Mahmudullah", "shortName": "Mahmudullah", "fullName": "Mohammad Mahmudullah", "displayName": "Mahmudullah"}, "team": {"id": "25", "name": "Bangladesh", "abbreviation": "BDESH", "displayName": "Bangladesh"}, "totalRuns": 16, "faced": 19, "fours": 2, "runs": 0, "sixes": 0}, "innings": {"id": "202064", "runRate": 6.02, "remainingBalls": 36, "byes": 0, "number": 1, "balls": 264, "noBalls": 0, "wickets": 3, "legByes": 0, "ballLimit": 300, "target": 0, "session": 1, "day": 1, "fallOfWickets": 0, "remainingOvers": 0.0, "totalRuns": 1, "wides": 0, "runs": 265}, "over": {"ball": 6, "balls": 6, "complete": true, "limit": 50.0, "maiden": 0, "noBall": 0, "wide": 0, "byes": 0, "legByes": 0, "number": 44, "runs": 12, "wickets": 0, "overs": 43.6, "actual": 43.6, "unique": 43.06}, "dismissal": {"dismissal": false, "bowled": false, "type": "", "bowler": {"athlete": {"id": "324358", "name": "Nuwan Pradeep", "shortName": "Pradeep", "fullName": "Aththachchi Nuwan Pradeep Roshan Fernando", "displayName": "Nuwan Pradeep"}}, "batsman": {"athlete": {"id": "56029", "name": "Mushfiqur Rahim", "shortName": "Mushfiqur", "fullName": "Mohammad Mushfiqur Rahim", "displayName": "Mushfiqur Rahim"}}, "fielder": {"athlete": {}}, "minutes": 0, "retiredText": ""}}, {"id": "144010", "clock": "00:00", "date": "2018-01-19T12:00", "playType": {"id": "1", "description": "run"}, "team": {"id": "25", "name": "Bangladesh", "abbreviation": "BDESH", "displayName": "Bangladesh"}, "mediaId": 0, "period": 1, "periodText": "1st innings", "preText": "", "text": "gets down for a big slog but it's a tad too full and he hammers it along the ground to deep midwicket", "postText": "", "shortText": "de Silva to Mushfiqur Rahim, 1 run", "homeScore": "266/3", "awayScore": "0", "scoreValue": 1, "sequence": 104401, "athletesInvolved": [{"id": "784379", "name": "Wanindu Hasaranga", "shortName": "de Silva", "displayName": "Wanindu Hasaranga"}, {"id": "56029", "name": "Mushfiqur Rahim", "shortName": "Mushfiqur", "displayName": "Mushfiqur Rahim"}], "speedKPH": "", "speedMPH": "", "bowler": {"athlete": {"id": "784379", "name": "Wanindu Hasaranga", "shortName": "de Silva", "fullName": "Pinnaduwage Wanindu Hasaranga de Silva", "displayName": "Wanindu Hasaranga"}, "team": {"id": "8", "name": "Sri Lanka", "abbreviation": "SL", "displayName": "Sri Lanka"}, "maidens": 0, "balls": 37, "wickets": 0, "overs": 6.1, "conceded": 40}, "otherBowler": {"athlete": {"id": "324358", "name": "Nuwan Pradeep", "shortName": "Pradeep", "fullName": "Aththachchi Nuwan Pradeep Roshan Fernando", "displayName": "Nuwan Pradeep"}, "team": {"id": "8", "name": "Sri Lanka", "abbreviation": "SL", "displayName": "Sri Lanka"}, "maidens": 0, "balls": 48, "wickets": 0, "overs": 8.0, "conceded": 52}, "batsman": {"athlete": {"id": "56029", "name": "Mushfiqur Rahim", "shortName": "Mushfiqur", "fullName": "Mohammad Mushfiqur Rahim", "displayName": "Mushfiqur Rahim"}, "team": {"id": "25", "name": "Bangladesh", "abbreviation": "BDESH", "displayName": "Bangladesh"}, "totalRuns": 53, "faced": 44, "fours": 3, "runs": 266, "sixes": 1}, "otherBatsman": {"athlete": {"id": "56025", "name": "Mahmudullah", "shortName": "Mahmudullah", "fullName": "Mohammad Mahmudullah", "displayName": "Mahmudullah"}, "team": {"id": "25", "name": "Bangladesh", "abbreviation": "BDESH", "displayName": "Bangladesh"}, "totalRuns": 16, "faced": 19, "fours": 2, "runs": 0, "sixes": 0}, "innings": {"id": "202064", "runRate": 6.02, "remainingBalls": 35, "byes": 0, "number": 1, "balls": 265, "noBalls": 0, "wickets": 3, "legByes": 0, "ballLimit": 300, "target": 0, "session": 1, "day": 1, "fallOfWickets": 0, "remainingOvers": 0.0, "totalRuns": 1, "wides": 0, "runs": 266}, "over": {"ball": 1, "balls": 6, "complete": false, "limit": 50.0, "maiden": 0, "noBall": 0, "wide": 0, "byes": 0, "legByes": 0, "number": 45, "runs": 12, "wickets": 0, "overs": 44.1, "actual": 44.1, "unique": 44.01}, "dismissal": {"dismissal": false, "bowled": false, "type": "", "bowler": {"athlete": {"id": "784379", "name": "Wanindu Hasaranga", "shortName": "de Silva", "fullName": "Pinnaduwage Wanindu Hasaranga de Silva", "displayName": "Wanindu Hasaranga"}}, "batsman": {"athlete": {"id": "56029", "name": "Mushfiqur Rahim", "shortName": "Mushfiqur", "fullName": "Mohammad Mushfiqur Rahim", "displayName": "Mushfiqur Rahim"}}, "fielder": {"athlete": {}}, "minutes": 0, "retiredText": ""}}, {"id": "144020", "clock": "00:00", "date": "2018-01-19T12:00", "playType": {"id": "1", "description": "run"}, "team": {"id": "25", "name": "Bangladesh", "abbreviation": "BDESH", "displayName": "Bangladesh"}, "mediaId": 0, "period": 1, "periodText": "1st innings", "preText": "", "text": "extremely full on off, squeezed out through the covers", "postText": "", "shortText": "de Silva to Mahmudullah, 1 run", "homeScore": "267/3", "awayScore": "0", "scoreValue": 1, "sequence": 104402, "athletesInvolved": [{"id": "784379", "name": "Wanindu Hasaranga", "shortName": "de Silva", "displayName": "Wanindu Hasaranga"}, {"id": "56025", "name": "Mahmudullah", "shortName": "Mahmudullah", "displayName": "Mahmudullah"}], "speedKPH": "", "speedMPH": "", "bowler": {"athlete": {"id": "784379", "name": "Wanindu Hasaranga", "shortName": "de Silva", "fullName": "Pinnaduwage Wanindu Hasaranga de Silva", "displayName": "Wanindu Hasaranga"}, "team": {"id": "8", "name": "Sri Lanka", "abbreviation": "SL", "displayName": "Sri Lanka"}, "maidens": 0, "balls": 38, "wickets": 0, "overs": 6.2, "conceded": 41}, "otherBowler": {"athlete": {"id": "324358", "name": "Nuwan Pradeep", "shortName": "Pradeep", "fullName": "Aththachchi Nuwan Pradeep Roshan Fernando", "displayName": "Nuwan Pradeep"}, "team": {"id": "8", "name": "Sri Lanka", "abbreviation": "SL", "displayName": "Sri Lanka"}, "maidens": 0, "balls": 48, "wickets": 0, "overs": 8.0, "conceded": 52}, "batsman": {"athlete": {"id": "56025", "name": "Mahmudullah", "shortName": "Mahmudullah", "fullName": "Mohammad Mahmudullah", "displayName": "Mahmudullah"}, "team": {"id": "25", "name": "Bangladesh", "abbreviation": "BDESH", "displayName": "Bangladesh"}, "totalRuns": 17, "faced": 20, "fours": 2, "runs": 267, "sixes": 0}, "otherBatsman": {"athlete": {"id": "56029", "name": "Mushfiqur Rahim", "shortName": "Mushfiqur", "fullName": "Mohammad Mushfiqur Rahim", "displayName": "Mushfiqur Rahim"}, "team": {"id": "25", "name": "Bangladesh", "abbreviation": "BDESH", "displayName": "Bangladesh"}, "totalRuns": 53, "faced": 44, "fours": 3, "runs": 0, "sixes": 1}, "innings": {"id": "202064", "runRate": 6.02, "remainingBalls": 34, "byes": 0, "number": 1, "balls": 266, "noBalls": 0, "wickets": 3, "legByes": 0, "ballLimit": 300, "target": 0, "session": 1, "day": 1, "fallOfWickets": 0, "remainingOvers": 0.0, "totalRuns": 1, "wides": 0, "runs": 267}, "over": {"ball": 2, "balls": 6, "complete": false, "limit": 50.0, "maiden": 0, "noBall": 0, "wide": 0, "byes": 0, "legByes": 0, "number": 45, "runs": 12, "wickets": 0, "overs": 44.2, "actual": 44.2, "unique": 44.02}, "dismissal": {"dismissal": false, "bowled": false, "type": "", "bowler": {"athlete": {"id": "784379", "name": "Wanindu Hasaranga", "shortName": "de Silva", "fullName": "Pinnaduwage Wanindu Hasaranga de Silva", "displayName": "Wanindu Hasaranga"}}, "batsman": {"athlete": {"id": "56025", "name": "Mahmudullah", "shortName": "Mahmudullah", "fullName": "Mohammad Mahmudullah", "displayName": "Mahmudullah"}}, "fielder": {"athlete": {}}, "minutes": 0, "retiredText": ""}}, {"id": "144030", "clock": "00:00", "date": "2018-01-19T12:00", "playType": {"id": "1", "description": "run"}, "team": {"id": "25", "name": "Bangladesh", "abbreviation": "BDESH", "displayName": "Bangladesh"}, "mediaId": 0, "period": 1, "periodText": "1st innings", "preText": "", "text": "length ball on middle, susses it out early and walks across for another scoop right over the keeper. Lack of pace means it won't carry to the boundary", "postText": "", "shortText": "de Silva to Mushfiqur Rahim, 2 runs", "homeScore": "269/3", "awayScore": "0", "scoreValue": 2, "sequence": 104403, "athletesInvolved": [{"id": "784379", "name": "Wanindu Hasaranga", "shortName": "de Silva", "displayName": "Wanindu Hasaranga"}, {"id": "56029", "name": "Mushfiqur Rahim", "shortName": "Mushfiqur", "displayName": "Mushfiqur Rahim"}], "speedKPH": "", "speedMPH": "", "bowler": {"athlete": {"id": "784379", "name": "Wanindu Hasaranga", "shortName": "de Silva", "fullName": "Pinnaduwage Wanindu Hasaranga de Silva", "displayName": "Wanindu Hasaranga"}, "team": {"id": "8", "name": "Sri Lanka", "abbreviation": "SL", "displayName": "Sri Lanka"}, "maidens": 0, "balls": 39, "wickets": 0, "overs": 6.3, "conceded": 43}, "otherBowler": {"athlete": {"id": "324358", "name": "Nuwan Pradeep", "shortName": "Pradeep", "fullName": "Aththachchi Nuwan Pradeep Roshan Fernando", "displayName": "Nuwan Pradeep"}, "team": {"id": "8", "name": "Sri Lanka", "abbreviation": "SL", "displayName": "Sri Lanka"}, "maidens": 0, "balls": 48, "wickets": 0, "overs": 8.0, "conceded": 52}, "batsman": {"athlete": {"id": "56029", "name": "Mushfiqur Rahim", "shortName": "Mushfiqur", "fullName": "Mohammad Mushfiqur Rahim", "displayName": "Mushfiqur Rahim"}, "team": {"id": "25", "name": "Bangladesh", "abbreviation": "BDESH", "displayName": "Bangladesh"}, "totalRuns": 55, "faced": 45, "fours": 3, "runs": 269, "sixes": 1}, "otherBatsman": {"athlete": {"id": "56025", "name": "Mahmudullah", "shortName": "Mahmudullah", "fullName": "Mohammad Mahmudullah", "displayName": "Mahmudullah"}, "team": {"id": "25", "name": "Bangladesh", "abbreviation": "BDESH", "displayName": "Bangladesh"}, "totalRuns": 17, "faced": 20, "fours": 2, "runs": 0, "sixes": 0}, "innings": {"id": "202064", "runRate": 6.04, "remainingBalls": 33, "byes": 0, "number": 1, "balls": 267, "noBalls": 0, "wickets": 3, "legByes": 0, "ballLimit": 300, "target": 0, "session": 1, "day": 1, "fallOfWickets": 0, "remainingOvers": 0.0, "totalRuns": 2, "wides": 0, "runs": 269}, "over": {"ball": 3, "balls": 6, "complete": false, "limit": 50.0, "maiden": 0, "noBall": 0, "wide": 0, "byes": 0, "legByes": 0, "number": 45, "runs": 12, "wickets": 0, "overs": 44.3, "actual": 44.3, "unique": 44.03}, "dismissal": {"dismissal": false, "bowled": false, "type": "", "bowler": {"athlete": {"id": "784379", "name": "Wanindu Hasaranga", "shortName": "de Silva", "fullName": "Pinnaduwage Wanindu Hasaranga de Silva", "displayName": "Wanindu Hasaranga"}}, "batsman": {"athlete": {"id": "56029", "name": "Mushfiqur Rahim", "shortName": "Mushfiqur", "fullName": "Mohammad Mushfiqur Rahim", "displayName": "Mushfiqur Rahim"}}, "fielder": {"athlete": {}}, "minutes": 0, "retiredText": ""}}, {"id": "144040", "clock": "00:00", "date": "2018-01-19T12:00", "playType": {"id": "1", "description": "run"}, "team": {"id": "25", "name": "Bangladesh", "abbreviation": "BDESH", "displayName": "Bangladesh"}, "mediaId": 0, "period": 1, "periodText": "1st innings", "preText": "", "text": "too full, slog-swept on the bounce to deep midwicket", "postText": "", "shortText": "de Silva to Mushfiqur Rahim, 1 run", "homeScore": "270/3", "awayScore": "0", "scoreValue": 1, "sequence": 104404, "athletesInvolved": [{"id": "784379", "name": "Wanindu Hasaranga", "shortName": "de Silva", "displayName": "Wanindu Hasaranga"}, {"id": "56029", "name": "Mushfiqur Rahim", "shortName": "Mushfiqur", "displayName": "Mushfiqur Rahim"}], "speedKPH": "", "speedMPH": "", "bowler": {"athlete": {"id": "784379", "name": "Wanindu Hasaranga", "shortName": "de Silva", "fullName": "Pinnaduwage Wanindu Hasaranga de Silva", "displayName": "Wanindu Hasaranga"}, "team": {"id": "8", "name": "Sri Lanka", "abbreviation": "SL", "displayName": "Sri Lanka"}, "maidens": 0, "balls": 40, "wickets": 0, "overs": 6.4, "conceded": 44}, "otherBowler": {"athlete": {"id": "324358", "name": "Nuwan Pradeep", "shortName": "Pradeep", "fullName": "Aththachchi Nuwan Pradeep Roshan Fernando", "displayName": "Nuwan Pradeep"}, "team": {"id": "8", "name": "Sri Lanka", "abbreviation": "SL", "displayName": "Sri Lanka"}, "maidens": 0, "balls": 48, "wickets": 0, "overs": 8.0, "conceded": 52}, "batsman": {"athlete": {"id": "56029", "name": "Mushfiqur Rahim", "shortName": "Mushfiqur", "fullName": "Mohammad Mushfiqur Rahim", "displayName": "Mushfiqur Rahim"}, "team": {"id": "25", "name": "Bangladesh", "abbreviation": "BDESH", "displayName": "Bangladesh"}, "totalRuns": 56, "faced": 46, "fours": 3, "runs": 270, "sixes": 1}, "otherBatsman": {"athlete": {"id": "56025", "name": "Mahmudullah", "shortName": "Mahmudullah", "fullName": "Mohammad Mahmudullah", "displayName": "Mahmudullah"}, "team": {"id": "25", "name": "Bangladesh", "abbreviation": "BDESH", "displayName": "Bangladesh"}, "totalRuns": 17, "faced": 20, "fours": 2, "runs": 0, "sixes": 0}, "innings": {"id": "202064", "runRate": 6.04, "remainingBalls": 32, "byes": 0, "number": 1, "balls": 268, "noBalls": 0, "wickets": 3, "legByes": 0, "ballLimit": 300, "target": 0, "session": 1, "day": 1, "fallOfWickets": 0, "remainingOvers": 0.0, "totalRuns": 1, "wides": 0, "runs": 270}, "over": {"ball": 4, "balls": 6, "complete": false, "limit": 50.0, "maiden": 0, "noBall": 0, "wide": 0, "byes": 0, "legByes": 0, "number": 45, "runs": 12, "wickets": 0, "overs": 44.4, "actual": 44.4, "unique": 44.04}, "dismissal": {"dismissal": false, "bowled": false, "type": "", "bowler": {"athlete": {"id": "784379", "name": "Wanindu Hasaranga", "shortName": "de Silva", "fullName": "Pinnaduwage Wanindu Hasaranga de Silva", "displayName": "Wanindu Hasaranga"}}, "batsman": {"athlete": {"id": "56029", "name": "Mushfiqur Rahim", "shortName": "Mushfiqur", "fullName": "Mohammad Mushfiqur Rahim", "displayName": "Mushfiqur Rahim"}}, "fielder": {"athlete": {}}, "minutes": 0, "retiredText": ""}}]}}